{
  "size": 8620,
  "opcodes": [
    {
      "op": "05",
      "offset": 0,
      "index": 0,
      "value": [
        "u16:398"
      ]
    },
    {
      "op": "44",
      "offset": 3,
      "index": 1,
      "value": [
        "　セシリアの肩先を強く突いた。",
        "/E"
      ]
    },
    {
      "op": "2F",
      "offset": 24,
      "index": 2,
      "value": [
        "u8:2",
        "u8:5"
      ]
    },
    {
      "op": "05",
      "offset": 27,
      "index": 3,
      "value": [
        "u16:1412"
      ]
    },
    {
      "op": "24",
      "offset": 30,
      "index": 4,
      "value": [
        "u8:4",
        "u8:116",
        "u8:1"
      ]
    },
    {
      "op": "4A",
      "offset": 34,
      "index": 5,
      "value": [
        "セシリア",
        "/E"
      ]
    },
    {
      "op": "44",
      "offset": 40,
      "index": 6,
      "value": [
        "「あっ、な、なにをするのっ」",
        "/E"
      ]
    },
    {
      "op": "4A",
      "offset": 56,
      "index": 7,
      "value": [
        "",
        "/E"
      ]
    },
    {
      "op": "44",
      "offset": 58,
      "index": 8,
      "value": [
        "　よろめいたセシリアは、昇降機の中に足を踏み入れる。",
        "/W"
      ]
    },
    {
      "op": "44",
      "offset": 93,
      "index": 9,
      "value": [
        "　他に乗客も乗務員の姿もない。",
        "/W"
      ]
    },
    {
      "op": "44",
      "offset": 117,
      "index": 10,
      "value": [
        "　続いて昇降機に入り、後ろ手に扉を閉めた。",
        "/E"
      ]
    },
    {
      "op": "24",
      "offset": 149,
      "index": 11,
      "value": [
        "u8:4",
        "u8:117",
        "u8:1"
      ]
    },
    {
      "op": "4A",
      "offset": 153,
      "index": 12,
      "value": [
        "セシリア",
        "/E"
      ]
    },
    {
      "op": "44",
      "offset": 159,
      "index": 13,
      "value": [
        "「な……なんのつもりですか？",
        "/C"
      ]
    },
    {
      "op": "44",
      "offset": 175,
      "index": 14,
      "value": [
        "　何を考えているのっ」",
        "/E"
      ]
    },
    {
      "op": "4A",
      "offset": 190,
      "index": 15,
      "value": [
        "",
        "/E"
      ]
    },
    {
      "op": "2F",
      "offset": 192,
      "index": 16,
      "value": [
        "u8:3",
        "u8:5"
      ]
    },
    {
      "op": "44",
      "offset": 195,
      "index": 17,
      "value": [
        "　黙ったまま、セシリアを昇降機の壁に押しつけた。",
        "/W"
      ]
    },
    {
      "op": "44",
      "offset": 227,
      "index": 18,
      "value": [
        "　青い瞳に怯えが走った。",
        "/W"
      ]
    },
    {
      "op": "44",
      "offset": 245,
      "index": 19,
      "value": [
        "　顔を逸らし、背中を向けるところを抱き寄せる。",
        "/E"
      ]
    },
    {
      "op": "44",
      "offset": 277,
      "index": 20,
      "value": [
        "　その瞬間、昇降機が動き始めた。",
        "/E"
      ]
    },
    {
      "op": "20",
      "offset": 302,
      "index": 21,
      "value": [
        "u8:3",
        "u8:255"
      ]
    },
    {
      "op": "43",
      "offset": 305,
      "index": 22,
      "value": []
    },
    {
      "op": "34",
      "offset": 306,
      "index": 23,
      "value": []
    },
    {
      "op": "28",
      "offset": 307,
      "index": 24,
      "value": [
        "u8:4",
        "u8:6",
        "u8:0"
      ]
    },
    {
      "op": "3B",
      "offset": 311,
      "index": 25,
      "value": [
        "u8:1",
        "u8:29",
        "u8:4",
        "u8:3"
      ]
    },
    {
      "op": "42",
      "offset": 316,
      "index": 26,
      "value": []
    },
    {
      "op": "44",
      "offset": 317,
      "index": 27,
      "value": [
        "　肩越しに、乳房のふくらみを掌で覆う。",
        "/W"
      ]
    },
    {
      "op": "44",
      "offset": 344,
      "index": 28,
      "value": [
        "　片手に余るほどの豊かな乳房は、どこまでもすべらかで柔らかい。",
        "/E"
      ]
    },
    {
      "op": "24",
      "offset": 384,
      "index": 29,
      "value": [
        "u8:4",
        "u8:118",
        "u8:1"
      ]
    },
    {
      "op": "4A",
      "offset": 388,
      "index": 30,
      "value": [
        "セシリア",
        "/E"
      ]
    },
    {
      "op": "44",
      "offset": 394,
      "index": 31,
      "value": [
        "「ヒッ！",
        "/C"
      ]
    },
    {
      "op": "44",
      "offset": 400,
      "index": 32,
      "value": [
        "　い、いや……やめてえっ」",
        "/E"
      ]
    },
    {
      "op": "4A",
      "offset": 415,
      "index": 33,
      "value": [
        "",
        "/E"
      ]
    },
    {
      "op": "44",
      "offset": 417,
      "index": 34,
      "value": [
        "　セシリアは、大胆なカットを施されたドレスしかまとっていない。",
        "/W"
      ]
    },
    {
      "op": "44",
      "offset": 453,
      "index": 35,
      "value": [
        "　乳首のすぐ上までしかない布地を、誇らしげに持ち上げている",
        "/C"
      ]
    },
    {
      "op": "44",
      "offset": 492,
      "index": 36,
      "value": [
        "ふくらみ。",
        "/E"
      ]
    },
    {
      "op": "44",
      "offset": 499,
      "index": 37,
      "value": [
        "　この造形の妙は、我が国の女性にはないものだ。",
        "/W"
      ]
    },
    {
      "op": "44",
      "offset": 531,
      "index": 38,
      "value": [
        "　乳房を押しつぶすようにして、ドレスの下に指を潜り込ませた。",
        "/E"
      ]
    },
    {
      "op": "24",
      "offset": 570,
      "index": 39,
      "value": [
        "u8:4",
        "u8:119",
        "u8:1"
      ]
    },
    {
      "op": "4A",
      "offset": 574,
      "index": 40,
      "value": [
        "セシリア",
        "/E"
      ]
    },
    {
      "op": "44",
      "offset": 580,
      "index": 41,
      "value": [
        "「ウア……や、やめて……！",
        "/C"
      ]
    },
    {
      "op": "44",
      "offset": 595,
      "index": 42,
      "value": [
        "　やめるのよ……ああ、ここをどこだと思っているの」",
        "/E"
      ]
    },
    {
      "op": "4A",
      "offset": 623,
      "index": 43,
      "value": [
        "",
        "/E"
      ]
    },
    {
      "op": "44",
      "offset": 625,
      "index": 44,
      "value": [
        "　悲痛な声音。",
        "/W"
      ]
    },
    {
      "op": "44",
      "offset": 638,
      "index": 45,
      "value": [
        "　当然だろう。",
        "/E"
      ]
    },
    {
      "op": "44",
      "offset": 649,
      "index": 46,
      "value": [
        "　今にも扉が開き、乗客が乗り込んでくるかもしれないのだ。",
        "/W"
      ]
    },
    {
      "op": "44",
      "offset": 686,
      "index": 47,
      "value": [
        "　身をくねらせるセシリアを、俺はしっかりと捕まえた。",
        "/W"
      ]
    },
    {
      "op": "44",
      "offset": 717,
      "index": 48,
      "value": [
        "　同時に、ドレスの下の乳首に触れる。",
        "/E"
      ]
    },
    {
      "op": "24",
      "offset": 743,
      "index": 49,
      "value": [
        "u8:4",
        "u8:120",
        "u8:1"
      ]
    },
    {
      "op": "4A",
      "offset": 747,
      "index": 50,
      "value": [
        "セシリア",
        "/E"
      ]
    },
    {
      "op": "44",
      "offset": 753,
      "index": 51,
      "value": [
        "「ふっ、いやあぁっ」",
        "/E"
      ]
    },
    {
      "op": "4A",
      "offset": 765,
      "index": 52,
      "value": [
        "",
        "/E"
      ]
    },
    {
      "op": "4A",
      "offset": 767,
      "index": 53,
      "value": [
        "N1",
        "/E"
      ]
    },
    {
      "op": "44",
      "offset": 770,
      "index": 54,
      "value": [
        "「何がいやなんだ？",
        "/C"
      ]
    },
    {
      "op": "44",
      "offset": 782,
      "index": 55,
      "value": [
        "　人に見られるかもしれないからか？」",
        "/E"
      ]
    },
    {
      "op": "4A",
      "offset": 804,
      "index": 56,
      "value": [
        "",
        "/E"
      ]
    },
    {
      "op": "44",
      "offset": 806,
      "index": 57,
      "value": [
        "　こくこくと、何度も頷くセシリア。",
        "/W"
      ]
    },
    {
      "op": "44",
      "offset": 828,
      "index": 58,
      "value": [
        "　俺は鼻で笑い、ドレスの胸元を引き下げた。",
        "/E"
      ]
    },
    {
      "op": "32",
      "offset": 858,
      "index": 59,
      "value": []
    },
    {
      "op": "28",
      "offset": 859,
      "index": 60,
      "value": [
        "u8:4",
        "u8:6",
        "u8:1"
      ]
    },
    {
      "op": "33",
      "offset": 863,
      "index": 61,
      "value": [
        "u8:2"
      ]
    },
    {
      "op": "4A",
      "offset": 865,
      "index": 62,
      "value": [
        "N1",
        "/E"
      ]
    },
    {
      "op": "44",
      "offset": 868,
      "index": 63,
      "value": [
        "「確かに婚約者のいる女が、こんなになってるところは見られたくない",
        "/C"
      ]
    },
    {
      "op": "44",
      "offset": 908,
      "index": 64,
      "value": [
        "　よなあ！？」",
        "/E"
      ]
    },
    {
      "op": "4A",
      "offset": 917,
      "index": 65,
      "value": [
        "",
        "/E"
      ]
    },
    {
      "op": "44",
      "offset": 919,
      "index": 66,
      "value": [
        "　勢い良く大きな乳房が飛び出す。",
        "/W"
      ]
    },
    {
      "op": "44",
      "offset": 944,
      "index": 67,
      "value": [
        "　ぷっくりとふくらんだ乳首が震えた。",
        "/E"
      ]
    },
    {
      "op": "24",
      "offset": 967,
      "index": 68,
      "value": [
        "u8:4",
        "u8:121",
        "u8:1"
      ]
    },
    {
      "op": "4A",
      "offset": 971,
      "index": 69,
      "value": [
        "セシリア",
        "/E"
      ]
    },
    {
      "op": "44",
      "offset": 977,
      "index": 70,
      "value": [
        "「キャアッ、いやあっ！」",
        "/E"
      ]
    },
    {
      "op": "4A",
      "offset": 991,
      "index": 71,
      "value": [
        "",
        "/E"
      ]
    },
    {
      "op": "4A",
      "offset": 993,
      "index": 72,
      "value": [
        "N1",
        "/E"
      ]
    },
    {
      "op": "44",
      "offset": 996,
      "index": 73,
      "value": [
        "「きゃあきゃあわめくなよ、狭いんだから」",
        "/E"
      ]
    },
    {
      "op": "4A",
      "offset": 1019,
      "index": 74,
      "value": [
        "",
        "/E"
      ]
    },
    {
      "op": "44",
      "offset": 1021,
      "index": 75,
      "value": [
        "　相手にもせず、後ろから回した手で、両方の乳房をすくい上げる。",
        "/W"
      ]
    },
    {
      "op": "44",
      "offset": 1064,
      "index": 76,
      "value": [
        "　やわやわと握ると、手に逆らわず変形する。",
        "/W"
      ]
    },
    {
      "op": "44",
      "offset": 1092,
      "index": 77,
      "value": [
        "　それでいて、ピンと張った肌は掌に吸いつくようだ。",
        "/E"
      ]
    },
    {
      "op": "44",
      "offset": 1123,
      "index": 78,
      "value": [
        "　親指と人差し指で、乳首を柔らかくこねてやった。",
        "/E"
      ]
    },
    {
      "op": "24",
      "offset": 1157,
      "index": 79,
      "value": [
        "u8:4",
        "u8:122",
        "u8:1"
      ]
    },
    {
      "op": "4A",
      "offset": 1161,
      "index": 80,
      "value": [
        "セシリア",
        "/E"
      ]
    },
    {
      "op": "44",
      "offset": 1167,
      "index": 81,
      "value": [
        "「クッ……ああ……あふ、うう……」",
        "/E"
      ]
    },
    {
      "op": "4A",
      "offset": 1186,
      "index": 82,
      "value": [
        "",
        "/E"
      ]
    },
    {
      "op": "44",
      "offset": 1188,
      "index": 83,
      "value": [
        "　大きく息を弾ませながら、セシリアが唇を噛む。",
        "/W"
      ]
    },
    {
      "op": "44",
      "offset": 1218,
      "index": 84,
      "value": [
        "　他人に見つかるかもしれない恐怖と、凌辱への嫌悪感。",
        "/W"
      ]
    },
    {
      "op": "44",
      "offset": 1256,
      "index": 85,
      "value": [
        "　しかしそれ以上に、こみ上げる快感があるのか。",
        "/E"
      ]
    },
    {
      "op": "4A",
      "offset": 1286,
      "index": 86,
      "value": [
        "N1",
        "/E"
      ]
    },
    {
      "op": "44",
      "offset": 1289,
      "index": 87,
      "value": [
        "「ふん、セシリア……こういうのが好きなのか？",
        "/C"
      ]
    },
    {
      "op": "44",
      "offset": 1314,
      "index": 88,
      "value": [
        "　今にも見つかりそうな緊張感が気持ちいいんだろ」",
        "/E"
      ]
    },
    {
      "op": "4A",
      "offset": 1347,
      "index": 89,
      "value": [
        "",
        "/E"
      ]
    },
    {
      "op": "44",
      "offset": 1349,
      "index": 90,
      "value": [
        "　長身のセシリアがビクッと震えた。",
        "/E"
      ]
    },
    {
      "op": "24",
      "offset": 1371,
      "index": 91,
      "value": [
        "u8:4",
        "u8:123",
        "u8:1"
      ]
    },
    {
      "op": "4A",
      "offset": 1375,
      "index": 92,
      "value": [
        "セシリア",
        "/E"
      ]
    },
    {
      "op": "44",
      "offset": 1381,
      "index": 93,
      "value": [
        "「そ……そんなことっ、ありませんっ」",
        "/E"
      ]
    },
    {
      "op": "4A",
      "offset": 1401,
      "index": 94,
      "value": [
        "",
        "/E"
      ]
    },
    {
      "op": "44",
      "offset": 1403,
      "index": 95,
      "value": [
        "　首を振る。",
        "/W"
      ]
    },
    {
      "op": "44",
      "offset": 1413,
      "index": 96,
      "value": [
        "　しかし薄桃色の乳首は、しこったように固くとがっている。",
        "/W"
      ]
    },
    {
      "op": "44",
      "offset": 1449,
      "index": 97,
      "value": [
        "　クニクニと弄ってやる。",
        "/E"
      ]
    },
    {
      "op": "4A",
      "offset": 1464,
      "index": 98,
      "value": [
        "N1",
        "/E"
      ]
    },
    {
      "op": "44",
      "offset": 1467,
      "index": 99,
      "value": [
        "「じゃあなんだ、この乳首は？",
        "/C"
      ]
    },
    {
      "op": "44",
      "offset": 1485,
      "index": 100,
      "value": [
        "　図星じゃないか」",
        "/E"
      ]
    },
    {
      "op": "4A",
      "offset": 1498,
      "index": 101,
      "value": [
        "",
        "/E"
      ]
    },
    {
      "op": "44",
      "offset": 1500,
      "index": 102,
      "value": [
        "　わざと笑いながら言ってやる。",
        "/W"
      ]
    },
    {
      "op": "44",
      "offset": 1519,
      "index": 103,
      "value": [
        "　白い西洋人特有の肌が、カッと上気する。",
        "/E"
      ]
    },
    {
      "op": "24",
      "offset": 1550,
      "index": 104,
      "value": [
        "u8:4",
        "u8:124",
        "u8:1"
      ]
    },
    {
      "op": "4A",
      "offset": 1554,
      "index": 105,
      "value": [
        "セシリア",
        "/E"
      ]
    },
    {
      "op": "44",
      "offset": 1560,
      "index": 106,
      "value": [
        "「いや……嘘です、そんな……わたしは違います……」",
        "/E"
      ]
    },
    {
      "op": "4A",
      "offset": 1589,
      "index": 107,
      "value": [
        "",
        "/E"
      ]
    },
    {
      "op": "44",
      "offset": 1591,
      "index": 108,
      "value": [
        "　半べそをかいたような顔で否定する。",
        "/E"
      ]
    },
    {
      "op": "4A",
      "offset": 1615,
      "index": 109,
      "value": [
        "N1",
        "/E"
      ]
    },
    {
      "op": "44",
      "offset": 1618,
      "index": 110,
      "value": [
        "「自分でもわかってるんだろ？",
        "/C"
      ]
    },
    {
      "op": "44",
      "offset": 1636,
      "index": 111,
      "value": [
        "　体が悦んでるって」",
        "/E"
      ]
    },
    {
      "op": "4A",
      "offset": 1650,
      "index": 112,
      "value": [
        "",
        "/E"
      ]
    },
    {
      "op": "44",
      "offset": 1652,
      "index": 113,
      "value": [
        "　うつむいた首筋を、長く伸ばした舌でなめ上げる。",
        "/E"
      ]
    },
    {
      "op": "24",
      "offset": 1684,
      "index": 114,
      "value": [
        "u8:4",
        "u8:125",
        "u8:1"
      ]
    },
    {
      "op": "4A",
      "offset": 1688,
      "index": 115,
      "value": [
        "セシリア",
        "/E"
      ]
    },
    {
      "op": "44",
      "offset": 1694,
      "index": 116,
      "value": [
        "「ハウッ、ウッウッ……い、いやあ……ウウンッ」",
        "/E"
      ]
    },
    {
      "op": "4A",
      "offset": 1719,
      "index": 117,
      "value": [
        "",
        "/E"
      ]
    },
    {
      "op": "44",
      "offset": 1721,
      "index": 118,
      "value": [
        "　力が抜ける。",
        "/W"
      ]
    },
    {
      "op": "44",
      "offset": 1732,
      "index": 119,
      "value": [
        "　もたれかかってくる体から、ドレスをまくり上げてやった。",
        "/W"
      ]
    },
    {
      "op": "44",
      "offset": 1764,
      "index": 120,
      "value": [
        "　長い裾を二掻き、三掻きして、張りつめた太腿と下着を露出させる。",
        "/E"
      ]
    },
    {
      "op": "32",
      "offset": 1811,
      "index": 121,
      "value": []
    },
    {
      "op": "28",
      "offset": 1812,
      "index": 122,
      "value": [
        "u8:4",
        "u8:6",
        "u8:2"
      ]
    },
    {
      "op": "33",
      "offset": 1816,
      "index": 123,
      "value": [
        "u8:2"
      ]
    },
    {
      "op": "24",
      "offset": 1818,
      "index": 124,
      "value": [
        "u8:4",
        "u8:126",
        "u8:1"
      ]
    },
    {
      "op": "4A",
      "offset": 1822,
      "index": 125,
      "value": [
        "セシリア",
        "/E"
      ]
    },
    {
      "op": "44",
      "offset": 1828,
      "index": 126,
      "value": [
        "「あ、あ……だめ、いけないっ！",
        "/C"
      ]
    },
    {
      "op": "44",
      "offset": 1845,
      "index": 127,
      "value": [
        "　こんな事されるなんて……あううっ、信じられない……！」",
        "/E"
      ]
    },
    {
      "op": "4A",
      "offset": 1877,
      "index": 128,
      "value": [
        "",
        "/E"
      ]
    },
    {
      "op": "44",
      "offset": 1879,
      "index": 129,
      "value": [
        "　手を滑らせ、脚の付け根に触れた。",
        "/W"
      ]
    },
    {
      "op": "44",
      "offset": 1904,
      "index": 130,
      "value": [
        "　きめ細かくしっとりした肌と、つやつやと滑りのいい下着の触感。",
        "/E"
      ]
    },
    {
      "op": "24",
      "offset": 1944,
      "index": 131,
      "value": [
        "u8:4",
        "u8:127",
        "u8:1"
      ]
    },
    {
      "op": "4A",
      "offset": 1948,
      "index": 132,
      "value": [
        "セシリア",
        "/E"
      ]
    },
    {
      "op": "44",
      "offset": 1954,
      "index": 133,
      "value": [
        "「だめ……だめ、人が来ます……っ」",
        "/E"
      ]
    },
    {
      "op": "4A",
      "offset": 1975,
      "index": 134,
      "value": [
        "",
        "/E"
      ]
    },
    {
      "op": "4A",
      "offset": 1977,
      "index": 135,
      "value": [
        "N1",
        "/E"
      ]
    },
    {
      "op": "44",
      "offset": 1980,
      "index": 136,
      "value": [
        "「来た方がいいんだろう、あんたは。",
        "/C"
      ]
    },
    {
      "op": "44",
      "offset": 2001,
      "index": 137,
      "value": [
        "　自分の恥ずかしいところを見て欲しいんだよな」",
        "/E"
      ]
    },
    {
      "op": "4A",
      "offset": 2031,
      "index": 138,
      "value": [
        "",
        "/E"
      ]
    },
    {
      "op": "44",
      "offset": 2033,
      "index": 139,
      "value": [
        "　下着に隠された秘部を、布地越しにさすってやる。",
        "/E"
      ]
    },
    {
      "op": "24",
      "offset": 2067,
      "index": 140,
      "value": [
        "u8:4",
        "u8:128",
        "u8:1"
      ]
    },
    {
      "op": "4A",
      "offset": 2071,
      "index": 141,
      "value": [
        "セシリア",
        "/E"
      ]
    },
    {
      "op": "44",
      "offset": 2077,
      "index": 142,
      "value": [
        "「ああ……おう、だ、だめ……違うわ。",
        "/C"
      ]
    },
    {
      "op": "44",
      "offset": 2098,
      "index": 143,
      "value": [
        "　わたしは……そんな女では、ハッ……アア、アアッ」",
        "/E"
      ]
    },
    {
      "op": "4A",
      "offset": 2126,
      "index": 144,
      "value": [
        "",
        "/E"
      ]
    },
    {
      "op": "44",
      "offset": 2128,
      "index": 145,
      "value": [
        "　何度もこすっているうちに、セシリアの力が抜けてきた。",
        "/W"
      ]
    },
    {
      "op": "44",
      "offset": 2161,
      "index": 146,
      "value": [
        "　わずかながら、指先に感じる布の感触が、湿り気を帯びてきたような",
        "/C"
      ]
    },
    {
      "op": "44",
      "offset": 2204,
      "index": 147,
      "value": [
        "気がする。",
        "/E"
      ]
    },
    {
      "op": "44",
      "offset": 2212,
      "index": 148,
      "value": [
        "　耳たぶに舌を這わせながら、下着に手をかけた。",
        "/W"
      ]
    },
    {
      "op": "44",
      "offset": 2243,
      "index": 149,
      "value": [
        "　脱がそうと思ったが、気を変えて布地の下に指を潜り込ませる。",
        "/E"
      ]
    },
    {
      "op": "24",
      "offset": 2285,
      "index": 150,
      "value": [
        "u8:4",
        "u8:129",
        "u8:1"
      ]
    },
    {
      "op": "4A",
      "offset": 2289,
      "index": 151,
      "value": [
        "セシリア",
        "/E"
      ]
    },
    {
      "op": "44",
      "offset": 2295,
      "index": 152,
      "value": [
        "「アウッ、そ、そんなところまでっ？",
        "/C"
      ]
    },
    {
      "op": "44",
      "offset": 2314,
      "index": 153,
      "value": [
        "　い、いけない……もう、それ以上はあっ」",
        "/E"
      ]
    },
    {
      "op": "4A",
      "offset": 2338,
      "index": 154,
      "value": [
        "",
        "/E"
      ]
    },
    {
      "op": "44",
      "offset": 2340,
      "index": 155,
      "value": [
        "　さわさわと薄い茂みに触れた。",
        "/W"
      ]
    },
    {
      "op": "44",
      "offset": 2360,
      "index": 156,
      "value": [
        "　さらに指を進めると、柔らかな肉に不意に亀裂が走る。",
        "/E"
      ]
    },
    {
      "op": "24",
      "offset": 2397,
      "index": 157,
      "value": [
        "u8:4",
        "u8:130",
        "u8:1"
      ]
    },
    {
      "op": "4A",
      "offset": 2401,
      "index": 158,
      "value": [
        "セシリア",
        "/E"
      ]
    },
    {
      "op": "44",
      "offset": 2407,
      "index": 159,
      "value": [
        "「あっ……あ、いやっ？",
        "/C"
      ]
    },
    {
      "op": "44",
      "offset": 2420,
      "index": 160,
      "value": [
        "　はあうっ、あああんっ」",
        "/E"
      ]
    },
    {
      "op": "4A",
      "offset": 2434,
      "index": 161,
      "value": [
        "",
        "/E"
      ]
    },
    {
      "op": "44",
      "offset": 2436,
      "index": 162,
      "value": [
        "　亀裂の奥の小さな粒に触れると、セシリアの体が跳ね上がった。",
        "/W"
      ]
    },
    {
      "op": "44",
      "offset": 2477,
      "index": 163,
      "value": [
        "　その拍子に、ぬるっと滑った指が肉ひだを割る。",
        "/E"
      ]
    },
    {
      "op": "24",
      "offset": 2508,
      "index": 164,
      "value": [
        "u8:4",
        "u8:131",
        "u8:1"
      ]
    },
    {
      "op": "4A",
      "offset": 2512,
      "index": 165,
      "value": [
        "セシリア",
        "/E"
      ]
    },
    {
      "op": "44",
      "offset": 2518,
      "index": 166,
      "value": [
        "「はっ……ああんっ！",
        "/C"
      ]
    },
    {
      "op": "44",
      "offset": 2530,
      "index": 167,
      "value": [
        "　そこは、ああっ、そこはあっ！」",
        "/E"
      ]
    },
    {
      "op": "4A",
      "offset": 2548,
      "index": 168,
      "value": [
        "",
        "/E"
      ]
    },
    {
      "op": "4A",
      "offset": 2550,
      "index": 169,
      "value": [
        "N1",
        "/E"
      ]
    },
    {
      "op": "44",
      "offset": 2553,
      "index": 170,
      "value": [
        "「濡れてる……いやらしい女」",
        "/E"
      ]
    },
    {
      "op": "4A",
      "offset": 2571,
      "index": 171,
      "value": [
        "",
        "/E"
      ]
    },
    {
      "op": "24",
      "offset": 2573,
      "index": 172,
      "value": [
        "u8:4",
        "u8:132",
        "u8:1"
      ]
    },
    {
      "op": "4A",
      "offset": 2577,
      "index": 173,
      "value": [
        "セシリア",
        "/E"
      ]
    },
    {
      "op": "44",
      "offset": 2583,
      "index": 174,
      "value": [
        "「ヒッ……アアアアッ！！」",
        "/E"
      ]
    },
    {
      "op": "4A",
      "offset": 2598,
      "index": 175,
      "value": [
        "",
        "/E"
      ]
    },
    {
      "op": "44",
      "offset": 2600,
      "index": 176,
      "value": [
        "　ぬかるんだ肉ひだは、充血して熱を持っている。",
        "/W"
      ]
    },
    {
      "op": "44",
      "offset": 2630,
      "index": 177,
      "value": [
        "　指先の感覚だけで、愛液を湧き出させている源泉を探った。",
        "/W"
      ]
    },
    {
      "op": "44",
      "offset": 2671,
      "index": 178,
      "value": [
        "　閉じた肉ひだの狭間を掻き回す動きに、女体がビクンビクン震える。",
        "/E"
      ]
    },
    {
      "op": "24",
      "offset": 2715,
      "index": 179,
      "value": [
        "u8:4",
        "u8:133",
        "u8:1"
      ]
    },
    {
      "op": "4A",
      "offset": 2719,
      "index": 180,
      "value": [
        "セシリア",
        "/E"
      ]
    },
    {
      "op": "44",
      "offset": 2725,
      "index": 181,
      "value": [
        "「お、おねがい……これ以上は、もうっ！",
        "/C"
      ]
    },
    {
      "op": "44",
      "offset": 2748,
      "index": 182,
      "value": [
        "　わたしはロ、ロバートがいるの……婚約者なのよ、ううっ」",
        "/E"
      ]
    },
    {
      "op": "4A",
      "offset": 2781,
      "index": 183,
      "value": [
        "",
        "/E"
      ]
    },
    {
      "op": "44",
      "offset": 2783,
      "index": 184,
      "value": [
        "　悶える動きに導かれるように、蜜壷の入り口にたどり着く。",
        "/W"
      ]
    },
    {
      "op": "44",
      "offset": 2821,
      "index": 185,
      "value": [
        "　少し力を入れるだけで、指がズルッと飲み込まれた。",
        "/E"
      ]
    },
    {
      "op": "24",
      "offset": 2854,
      "index": 186,
      "value": [
        "u8:4",
        "u8:134",
        "u8:1"
      ]
    },
    {
      "op": "4A",
      "offset": 2858,
      "index": 187,
      "value": [
        "セシリア",
        "/E"
      ]
    },
    {
      "op": "44",
      "offset": 2864,
      "index": 188,
      "value": [
        "「アアアッ、ハアアーッ！」",
        "/E"
      ]
    },
    {
      "op": "4A",
      "offset": 2879,
      "index": 189,
      "value": [
        "",
        "/E"
      ]
    },
    {
      "op": "44",
      "offset": 2881,
      "index": 190,
      "value": [
        "　そのまま付け根まで差し入れる。",
        "/W"
      ]
    },
    {
      "op": "44",
      "offset": 2903,
      "index": 191,
      "value": [
        "　熱い内壁がきつく指を締めつけてきた。",
        "/W"
      ]
    },
    {
      "op": "44",
      "offset": 2929,
      "index": 192,
      "value": [
        "　軽くひっかくように関節を曲げ、ゆっくりと引き出してやる。",
        "/E"
      ]
    },
    {
      "op": "24",
      "offset": 2966,
      "index": 193,
      "value": [
        "u8:4",
        "u8:135",
        "u8:1"
      ]
    },
    {
      "op": "4A",
      "offset": 2970,
      "index": 194,
      "value": [
        "セシリア",
        "/E"
      ]
    },
    {
      "op": "44",
      "offset": 2976,
      "index": 195,
      "value": [
        "「おお、ああふっ！",
        "/C"
      ]
    },
    {
      "op": "44",
      "offset": 2987,
      "index": 196,
      "value": [
        "　あ、あ、あ……ウアアッ」",
        "/E"
      ]
    },
    {
      "op": "4A",
      "offset": 3002,
      "index": 197,
      "value": [
        "",
        "/E"
      ]
    },
    {
      "op": "4A",
      "offset": 3004,
      "index": 198,
      "value": [
        "N1",
        "/E"
      ]
    },
    {
      "op": "44",
      "offset": 3007,
      "index": 199,
      "value": [
        "「熱いぜ……。",
        "/C"
      ]
    },
    {
      "op": "44",
      "offset": 3017,
      "index": 200,
      "value": [
        "　奥までビッショリ濡れてる」",
        "/E"
      ]
    },
    {
      "op": "4A",
      "offset": 3035,
      "index": 201,
      "value": [
        "",
        "/E"
      ]
    },
    {
      "op": "24",
      "offset": 3037,
      "index": 202,
      "value": [
        "u8:4",
        "u8:136",
        "u8:1"
      ]
    },
    {
      "op": "4A",
      "offset": 3041,
      "index": 203,
      "value": [
        "セシリア",
        "/E"
      ]
    },
    {
      "op": "44",
      "offset": 3047,
      "index": 204,
      "value": [
        "「ウ……ふあぁぁんっ」",
        "/E"
      ]
    },
    {
      "op": "4A",
      "offset": 3060,
      "index": 205,
      "value": [
        "",
        "/E"
      ]
    },
    {
      "op": "44",
      "offset": 3062,
      "index": 206,
      "value": [
        "　言葉で嬲ってやると、案の定セシリアは激しい反応を見せた。",
        "/W"
      ]
    },
    {
      "op": "44",
      "offset": 3102,
      "index": 207,
      "value": [
        "　どうやら辱められるのがいいらしい。",
        "/E"
      ]
    },
    {
      "op": "44",
      "offset": 3123,
      "index": 208,
      "value": [
        "　と、そのとき、昇降機の動きが止まった。",
        "/W"
      ]
    },
    {
      "op": "44",
      "offset": 3150,
      "index": 209,
      "value": [
        "　扉が開くのか。",
        "/W"
      ]
    },
    {
      "op": "44",
      "offset": 3162,
      "index": 210,
      "value": [
        "　指を抜き、乱れたドレスを手早くなおした。",
        "/E"
      ]
    },
    {
      "op": "24",
      "offset": 3190,
      "index": 211,
      "value": [
        "u8:4",
        "u8:137",
        "u8:1"
      ]
    },
    {
      "op": "4A",
      "offset": 3194,
      "index": 212,
      "value": [
        "セシリア",
        "/E"
      ]
    },
    {
      "op": "44",
      "offset": 3200,
      "index": 213,
      "value": [
        "「……ア？",
        "/C"
      ]
    },
    {
      "op": "44",
      "offset": 3207,
      "index": 214,
      "value": [
        "　ハウ……ウン？」",
        "/E"
      ]
    },
    {
      "op": "4A",
      "offset": 3218,
      "index": 215,
      "value": [
        "",
        "/E"
      ]
    },
    {
      "op": "44",
      "offset": 3220,
      "index": 216,
      "value": [
        "　うつろな眼で、怪訝そうに見上げる。",
        "/W"
      ]
    },
    {
      "op": "44",
      "offset": 3245,
      "index": 217,
      "value": [
        "　昇降機の中にいるという事すら、忘れてしまったか。",
        "/E"
      ]
    },
    {
      "op": "44",
      "offset": 3278,
      "index": 218,
      "value": [
        "　間一髪、機械音とともに扉が開いた。",
        "/W"
      ]
    },
    {
      "op": "44",
      "offset": 3306,
      "index": 219,
      "value": [
        "　身なりのいい男が乗り込んでくる。",
        "/W"
      ]
    },
    {
      "op": "44",
      "offset": 3329,
      "index": 220,
      "value": [
        "　俺はセシリアの腕を取り、入れ違いに昇降機を降りた。",
        "/E"
      ]
    },
    {
      "op": "44",
      "offset": 3366,
      "index": 221,
      "value": [
        "　不審げな表情で、男が振り向くのが見えた。",
        "/W"
      ]
    },
    {
      "op": "44",
      "offset": 3397,
      "index": 222,
      "value": [
        "　セシリアの撒き散らした、刺激的な女の匂いでも嗅ぎつけたか。",
        "/W"
      ]
    },
    {
      "op": "44",
      "offset": 3437,
      "index": 223,
      "value": [
        "　そのとき、男の鼻先で扉が閉まった。",
        "/E"
      ]
    },
    {
      "op": "20",
      "offset": 3462,
      "index": 224,
      "value": [
        "u8:1",
        "u8:255"
      ]
    },
    {
      "op": "43",
      "offset": 3465,
      "index": 225,
      "value": []
    },
    {
      "op": "34",
      "offset": 3466,
      "index": 226,
      "value": []
    },
    {
      "op": "27",
      "offset": 3467,
      "index": 227,
      "value": [
        "u16:45"
      ]
    },
    {
      "op": "2E",
      "offset": 3470,
      "index": 228,
      "value": [
        "u8:4",
        "u8:7",
        "u8:2",
        "u8:0"
      ]
    },
    {
      "op": "3B",
      "offset": 3475,
      "index": 229,
      "value": [
        "u8:1",
        "u8:29",
        "u8:4",
        "u8:3"
      ]
    },
    {
      "op": "42",
      "offset": 3480,
      "index": 230,
      "value": []
    },
    {
      "op": "24",
      "offset": 3481,
      "index": 231,
      "value": [
        "u8:4",
        "u8:138",
        "u8:1"
      ]
    },
    {
      "op": "4A",
      "offset": 3485,
      "index": 232,
      "value": [
        "セシリア",
        "/E"
      ]
    },
    {
      "op": "44",
      "offset": 3491,
      "index": 233,
      "value": [
        "「ア……はあはあ……はあはあ……」",
        "/E"
      ]
    },
    {
      "op": "4A",
      "offset": 3510,
      "index": 234,
      "value": [
        "",
        "/E"
      ]
    },
    {
      "op": "44",
      "offset": 3512,
      "index": 235,
      "value": [
        "　頬を上気させたセシリアは、おとなしく腕を取られたままだ。",
        "/E"
      ]
    },
    {
      "op": "2E",
      "offset": 3548,
      "index": 236,
      "value": [
        "u8:32",
        "u8:1",
        "u8:3",
        "u8:5"
      ]
    },
    {
      "op": "4A",
      "offset": 3553,
      "index": 237,
      "value": [
        "N1",
        "/E"
      ]
    },
    {
      "op": "44",
      "offset": 3556,
      "index": 238,
      "value": [
        "「何をしている、こっちに来い」",
        "/E"
      ]
    },
    {
      "op": "4A",
      "offset": 3575,
      "index": 239,
      "value": [
        "",
        "/E"
      ]
    },
    {
      "op": "44",
      "offset": 3577,
      "index": 240,
      "value": [
        "　乱暴に引っ張り、歩き出す。",
        "/W"
      ]
    },
    {
      "op": "44",
      "offset": 3599,
      "index": 241,
      "value": [
        "　このままじゃこっちが収まらない。",
        "/E"
      ]
    },
    {
      "op": "32",
      "offset": 3619,
      "index": 242,
      "value": []
    },
    {
      "op": "2F",
      "offset": 3620,
      "index": 243,
      "value": [
        "u8:2",
        "u8:0"
      ]
    },
    {
      "op": "2F",
      "offset": 3623,
      "index": 244,
      "value": [
        "u8:3",
        "u8:0"
      ]
    },
    {
      "op": "33",
      "offset": 3626,
      "index": 245,
      "value": [
        "u8:4"
      ]
    },
    {
      "op": "44",
      "offset": 3628,
      "index": 246,
      "value": [
        "　フロアを歩いていると、西洋式の便所を見つけた。",
        "/W"
      ]
    },
    {
      "op": "44",
      "offset": 3661,
      "index": 247,
      "value": [
        "　ここなら邪魔も入るまい。",
        "/W"
      ]
    },
    {
      "op": "44",
      "offset": 3679,
      "index": 248,
      "value": [
        "　セシリアを引きずるようにして中へ連れ込む。",
        "/E"
      ]
    },
    {
      "op": "44",
      "offset": 3707,
      "index": 249,
      "value": [
        "　足がもつれているのか、さほど抵抗もなくヨロヨロとついてきた。",
        "/W"
      ]
    },
    {
      "op": "44",
      "offset": 3743,
      "index": 250,
      "value": [
        "　我に返られると面倒だ。",
        "/W"
      ]
    },
    {
      "op": "44",
      "offset": 3761,
      "index": 251,
      "value": [
        "　俺は黙ったまま、奥の個室にセシリアを押し込んだ。",
        "/E"
      ]
    },
    {
      "op": "44",
      "offset": 3795,
      "index": 252,
      "value": [
        "　後ろ手に鍵をかける。",
        "/W"
      ]
    },
    {
      "op": "44",
      "offset": 3811,
      "index": 253,
      "value": [
        "　カチリ。",
        "/E"
      ]
    },
    {
      "op": "44",
      "offset": 3818,
      "index": 254,
      "value": [
        "　固い音が響き、青い目が動揺する。",
        "/W"
      ]
    },
    {
      "op": "44",
      "offset": 3844,
      "index": 255,
      "value": [
        "　俺を見る頼りなげな視線。",
        "/E"
      ]
    },
    {
      "op": "4A",
      "offset": 3864,
      "index": 256,
      "value": [
        "N1",
        "/E"
      ]
    },
    {
      "op": "44",
      "offset": 3867,
      "index": 257,
      "value": [
        "「今さら、やめてなんて言うなよ。",
        "/C"
      ]
    },
    {
      "op": "44",
      "offset": 3887,
      "index": 258,
      "value": [
        "　逃げられるときに逃げなかったのは、あんたの方だ」",
        "/E"
      ]
    },
    {
      "op": "4A",
      "offset": 3917,
      "index": 259,
      "value": [
        "",
        "/E"
      ]
    },
    {
      "op": "44",
      "offset": 3919,
      "index": 260,
      "value": [
        "　有無を言わせず両肩を押さえ、便器の蓋に座らせた。",
        "/W"
      ]
    },
    {
      "op": "44",
      "offset": 3956,
      "index": 261,
      "value": [
        "　すでに固くそそり立ち、熱く脈打つ分身を引き出して突きつけた。",
        "/W"
      ]
    },
    {
      "op": "44",
      "offset": 3999,
      "index": 262,
      "value": [
        "　怯えたように、セシリアは目をそらせる。",
        "/E"
      ]
    },
    {
      "op": "44",
      "offset": 4023,
      "index": 263,
      "value": [
        "　俺は一歩進んで、白磁のような頬に剛直を押しつけた。",
        "/E"
      ]
    },
    {
      "op": "4A",
      "offset": 4061,
      "index": 264,
      "value": [
        "N1",
        "/E"
      ]
    },
    {
      "op": "44",
      "offset": 4064,
      "index": 265,
      "value": [
        "「本当に嫌ならいくらでも逃げられたはずだ。",
        "/C"
      ]
    },
    {
      "op": "44",
      "offset": 4091,
      "index": 266,
      "value": [
        "　だがあんたは逃げなかった、という事は」",
        "/E"
      ]
    },
    {
      "op": "4A",
      "offset": 4115,
      "index": 267,
      "value": [
        "",
        "/E"
      ]
    },
    {
      "op": "20",
      "offset": 4117,
      "index": 268,
      "value": [
        "u8:3",
        "u8:255"
      ]
    },
    {
      "op": "43",
      "offset": 4120,
      "index": 269,
      "value": []
    },
    {
      "op": "34",
      "offset": 4121,
      "index": 270,
      "value": []
    },
    {
      "op": "28",
      "offset": 4122,
      "index": 271,
      "value": [
        "u8:4",
        "u8:7",
        "u8:0"
      ]
    },
    {
      "op": "3B",
      "offset": 4126,
      "index": 272,
      "value": [
        "u8:1",
        "u8:29",
        "u8:4",
        "u8:3"
      ]
    },
    {
      "op": "42",
      "offset": 4131,
      "index": 273,
      "value": []
    },
    {
      "op": "24",
      "offset": 4132,
      "index": 274,
      "value": [
        "u8:4",
        "u8:139",
        "u8:1"
      ]
    },
    {
      "op": "4A",
      "offset": 4136,
      "index": 275,
      "value": [
        "セシリア",
        "/E"
      ]
    },
    {
      "op": "44",
      "offset": 4142,
      "index": 276,
      "value": [
        "「ちっ、違うわ、そんな女じゃ……！」",
        "/E"
      ]
    },
    {
      "op": "4A",
      "offset": 4164,
      "index": 277,
      "value": [
        "",
        "/E"
      ]
    },
    {
      "op": "44",
      "offset": 4166,
      "index": 278,
      "value": [
        "　抗議しようと開いた口に、すかさず赤黒い先端を突っ込む。",
        "/E"
      ]
    },
    {
      "op": "24",
      "offset": 4206,
      "index": 279,
      "value": [
        "u8:4",
        "u8:140",
        "u8:1"
      ]
    },
    {
      "op": "4A",
      "offset": 4210,
      "index": 280,
      "value": [
        "セシリア",
        "/E"
      ]
    },
    {
      "op": "44",
      "offset": 4216,
      "index": 281,
      "value": [
        "「ムグウッ！？」",
        "/E"
      ]
    },
    {
      "op": "4A",
      "offset": 4226,
      "index": 282,
      "value": [
        "",
        "/E"
      ]
    },
    {
      "op": "44",
      "offset": 4228,
      "index": 283,
      "value": [
        "　とろけそうに熱い感覚に包み込まれる。",
        "/W"
      ]
    },
    {
      "op": "44",
      "offset": 4254,
      "index": 284,
      "value": [
        "　快感にうめきながら、吐き出されないように髪をつかんで固定した。",
        "/E"
      ]
    },
    {
      "op": "24",
      "offset": 4295,
      "index": 285,
      "value": [
        "u8:4",
        "u8:141",
        "u8:1"
      ]
    },
    {
      "op": "4A",
      "offset": 4299,
      "index": 286,
      "value": [
        "セシリア",
        "/E"
      ]
    },
    {
      "op": "44",
      "offset": 4305,
      "index": 287,
      "value": [
        "「ウッムウ……ハグ、ウブ……ンッ……ムウッ！」",
        "/E"
      ]
    },
    {
      "op": "4A",
      "offset": 4330,
      "index": 288,
      "value": [
        "",
        "/E"
      ]
    },
    {
      "op": "44",
      "offset": 4332,
      "index": 289,
      "value": [
        "　暴れる舌の動きが、しびれるほどの快感を生む。",
        "/W"
      ]
    },
    {
      "op": "44",
      "offset": 4363,
      "index": 290,
      "value": [
        "　髪の毛をつかんだまま腰を動かし始めた。",
        "/E"
      ]
    },
    {
      "op": "4A",
      "offset": 4390,
      "index": 291,
      "value": [
        "N1",
        "/E"
      ]
    },
    {
      "op": "44",
      "offset": 4393,
      "index": 292,
      "value": [
        "「……しっかり気持ちよくしろよ。",
        "/C"
      ]
    },
    {
      "op": "44",
      "offset": 4413,
      "index": 293,
      "value": [
        "　ちゃんとイカせてほしいだろ」",
        "/E"
      ]
    },
    {
      "op": "4A",
      "offset": 4430,
      "index": 294,
      "value": [
        "",
        "/E"
      ]
    },
    {
      "op": "24",
      "offset": 4432,
      "index": 295,
      "value": [
        "u8:4",
        "u8:142",
        "u8:1"
      ]
    },
    {
      "op": "4A",
      "offset": 4436,
      "index": 296,
      "value": [
        "セシリア",
        "/E"
      ]
    },
    {
      "op": "44",
      "offset": 4442,
      "index": 297,
      "value": [
        "「ウウ……アム、ウウン……ンク、ンク……ウウムッ」",
        "/E"
      ]
    },
    {
      "op": "4A",
      "offset": 4469,
      "index": 298,
      "value": [
        "",
        "/E"
      ]
    },
    {
      "op": "44",
      "offset": 4471,
      "index": 299,
      "value": [
        "　苦しげなセシリアは、観念したようにまつげを伏せた。",
        "/W"
      ]
    },
    {
      "op": "44",
      "offset": 4503,
      "index": 300,
      "value": [
        "　恐る恐るといった風情で、舌が触れてくる。",
        "/W"
      ]
    },
    {
      "op": "44",
      "offset": 4532,
      "index": 301,
      "value": [
        "　ぎこちない動きが物足りない。",
        "/E"
      ]
    },
    {
      "op": "44",
      "offset": 4552,
      "index": 302,
      "value": [
        "　歯がゆさに、深々と突き入れてやった。",
        "/E"
      ]
    },
    {
      "op": "24",
      "offset": 4577,
      "index": 303,
      "value": [
        "u8:4",
        "u8:143",
        "u8:1"
      ]
    },
    {
      "op": "4A",
      "offset": 4581,
      "index": 304,
      "value": [
        "セシリア",
        "/E"
      ]
    },
    {
      "op": "44",
      "offset": 4587,
      "index": 305,
      "value": [
        "「グウッ、ウムアッ！",
        "/C"
      ]
    },
    {
      "op": "44",
      "offset": 4599,
      "index": 306,
      "value": [
        "　ウ、オウッ……オエエッ」",
        "/E"
      ]
    },
    {
      "op": "4A",
      "offset": 4614,
      "index": 307,
      "value": [
        "",
        "/E"
      ]
    },
    {
      "op": "44",
      "offset": 4616,
      "index": 308,
      "value": [
        "　のどの奥を突かれ、セシリアの目に涙がにじむ。",
        "/W"
      ]
    },
    {
      "op": "44",
      "offset": 4645,
      "index": 309,
      "value": [
        "　とっさに吐き出そうとする動きを、髪を引っ張って止める。",
        "/E"
      ]
    },
    {
      "op": "24",
      "offset": 4682,
      "index": 310,
      "value": [
        "u8:4",
        "u8:144",
        "u8:1"
      ]
    },
    {
      "op": "4A",
      "offset": 4686,
      "index": 311,
      "value": [
        "セシリア",
        "/E"
      ]
    },
    {
      "op": "44",
      "offset": 4692,
      "index": 312,
      "value": [
        "「ウグゥゥ、アウウ……オグウ……！」",
        "/E"
      ]
    },
    {
      "op": "4A",
      "offset": 4712,
      "index": 313,
      "value": [
        "",
        "/E"
      ]
    },
    {
      "op": "44",
      "offset": 4714,
      "index": 314,
      "value": [
        "　恨めしげに見上げるセシリア。",
        "/W"
      ]
    },
    {
      "op": "44",
      "offset": 4734,
      "index": 315,
      "value": [
        "　構わず腰を動かす。",
        "/W"
      ]
    },
    {
      "op": "44",
      "offset": 4749,
      "index": 316,
      "value": [
        "　美しい顔が動きに合わせて歪む。",
        "/E"
      ]
    },
    {
      "op": "44",
      "offset": 4772,
      "index": 317,
      "value": [
        "　とてもいやらしく、それでいて美しい眺めだった。",
        "/E"
      ]
    },
    {
      "op": "32",
      "offset": 4800,
      "index": 318,
      "value": []
    },
    {
      "op": "28",
      "offset": 4801,
      "index": 319,
      "value": [
        "u8:4",
        "u8:7",
        "u8:1"
      ]
    },
    {
      "op": "33",
      "offset": 4805,
      "index": 320,
      "value": [
        "u8:2"
      ]
    },
    {
      "op": "24",
      "offset": 4807,
      "index": 321,
      "value": [
        "u8:4",
        "u8:145",
        "u8:1"
      ]
    },
    {
      "op": "4A",
      "offset": 4811,
      "index": 322,
      "value": [
        "セシリア",
        "/E"
      ]
    },
    {
      "op": "44",
      "offset": 4817,
      "index": 323,
      "value": [
        "「ウブッ、アブッ……ちゅるっ、ちゃぷっ……ムググッ」",
        "/E"
      ]
    },
    {
      "op": "4A",
      "offset": 4845,
      "index": 324,
      "value": [
        "",
        "/E"
      ]
    },
    {
      "op": "44",
      "offset": 4847,
      "index": 325,
      "value": [
        "　柔らかな粘膜の感触に俺は高ぶった。",
        "/W"
      ]
    },
    {
      "op": "44",
      "offset": 4874,
      "index": 326,
      "value": [
        "　先走りの液が先端から漏れる。",
        "/W"
      ]
    },
    {
      "op": "44",
      "offset": 4897,
      "index": 327,
      "value": [
        "　と、セシリアの表情が変わった。",
        "/E"
      ]
    },
    {
      "op": "24",
      "offset": 4918,
      "index": 328,
      "value": [
        "u8:4",
        "u8:146",
        "u8:1"
      ]
    },
    {
      "op": "4A",
      "offset": 4922,
      "index": 329,
      "value": [
        "セシリア",
        "/E"
      ]
    },
    {
      "op": "44",
      "offset": 4928,
      "index": 330,
      "value": [
        "「ハアン……ウブ、クムウン……ハア、ハア……じゅるっじゅるっ」",
        "/E"
      ]
    },
    {
      "op": "4A",
      "offset": 4961,
      "index": 331,
      "value": [
        "",
        "/E"
      ]
    },
    {
      "op": "44",
      "offset": 4963,
      "index": 332,
      "value": [
        "　積極的に唇を締めつけてくる。",
        "/W"
      ]
    },
    {
      "op": "44",
      "offset": 4985,
      "index": 333,
      "value": [
        "　舌を巻きつけ、しゃぶってくる。",
        "/W"
      ]
    },
    {
      "op": "44",
      "offset": 5005,
      "index": 334,
      "value": [
        "　予想以上に熱心で慣れた様子だった。",
        "/E"
      ]
    },
    {
      "op": "4A",
      "offset": 5034,
      "index": 335,
      "value": [
        "N1",
        "/E"
      ]
    },
    {
      "op": "44",
      "offset": 5037,
      "index": 336,
      "value": [
        "「セシリア……どういう風の吹き回しだ？」",
        "/E"
      ]
    },
    {
      "op": "4A",
      "offset": 5062,
      "index": 337,
      "value": [
        "",
        "/E"
      ]
    },
    {
      "op": "44",
      "offset": 5064,
      "index": 338,
      "value": [
        "　冷やかす声も耳に入らないのか。",
        "/E"
      ]
    },
    {
      "op": "32",
      "offset": 5086,
      "index": 339,
      "value": []
    },
    {
      "op": "28",
      "offset": 5087,
      "index": 340,
      "value": [
        "u8:4",
        "u8:7",
        "u8:2"
      ]
    },
    {
      "op": "33",
      "offset": 5091,
      "index": 341,
      "value": [
        "u8:2"
      ]
    },
    {
      "op": "24",
      "offset": 5093,
      "index": 342,
      "value": [
        "u8:4",
        "u8:147",
        "u8:1"
      ]
    },
    {
      "op": "4A",
      "offset": 5097,
      "index": 343,
      "value": [
        "セシリア",
        "/E"
      ]
    },
    {
      "op": "44",
      "offset": 5103,
      "index": 344,
      "value": [
        "「ハムウ、クムンッ、ウフ……じゅぷ、じゅくっ……アアンッ」",
        "/E"
      ]
    },
    {
      "op": "4A",
      "offset": 5134,
      "index": 345,
      "value": [
        "",
        "/E"
      ]
    },
    {
      "op": "44",
      "offset": 5136,
      "index": 346,
      "value": [
        "　執拗な愛撫だった。",
        "/W"
      ]
    },
    {
      "op": "44",
      "offset": 5152,
      "index": 347,
      "value": [
        "　熱く濡れた口の中で、分身が大きくふくれる。",
        "/W"
      ]
    },
    {
      "op": "44",
      "offset": 5183,
      "index": 348,
      "value": [
        "　昇り詰め、解き放たれたがっている。",
        "/E"
      ]
    },
    {
      "op": "24",
      "offset": 5207,
      "index": 349,
      "value": [
        "u8:4",
        "u8:148",
        "u8:1"
      ]
    },
    {
      "op": "4A",
      "offset": 5211,
      "index": 350,
      "value": [
        "セシリア",
        "/E"
      ]
    },
    {
      "op": "44",
      "offset": 5217,
      "index": 351,
      "value": [
        "「ハウウ、アウウ……ウウ、ハアッ……グム……アフウッ」",
        "/E"
      ]
    },
    {
      "op": "4A",
      "offset": 5246,
      "index": 352,
      "value": [
        "",
        "/E"
      ]
    },
    {
      "op": "44",
      "offset": 5248,
      "index": 353,
      "value": [
        "　必死に息をつきながら、剛直に舌を這わせてくる。",
        "/W"
      ]
    },
    {
      "op": "44",
      "offset": 5281,
      "index": 354,
      "value": [
        "　瞳はうっとり溶けて、悦んでいるようだ。",
        "/W"
      ]
    },
    {
      "op": "44",
      "offset": 5306,
      "index": 355,
      "value": [
        "　執拗な舌の動き。",
        "/E"
      ]
    },
    {
      "op": "44",
      "offset": 5321,
      "index": 356,
      "value": [
        "　このままでは危なかった。",
        "/E"
      ]
    },
    {
      "op": "4A",
      "offset": 5337,
      "index": 357,
      "value": [
        "N1",
        "/E"
      ]
    },
    {
      "op": "44",
      "offset": 5340,
      "index": 358,
      "value": [
        "「……もういい！」",
        "/E"
      ]
    },
    {
      "op": "4A",
      "offset": 5351,
      "index": 359,
      "value": [
        "",
        "/E"
      ]
    },
    {
      "op": "43",
      "offset": 5353,
      "index": 360,
      "value": []
    },
    {
      "op": "34",
      "offset": 5354,
      "index": 361,
      "value": []
    },
    {
      "op": "27",
      "offset": 5355,
      "index": 362,
      "value": [
        "u16:256"
      ]
    },
    {
      "op": "3B",
      "offset": 5358,
      "index": 363,
      "value": [
        "u8:1",
        "u8:29",
        "u8:4",
        "u8:3"
      ]
    },
    {
      "op": "42",
      "offset": 5363,
      "index": 364,
      "value": []
    },
    {
      "op": "44",
      "offset": 5364,
      "index": 365,
      "value": [
        "　腰を引き、肉棒を引き出す。",
        "/W"
      ]
    },
    {
      "op": "44",
      "offset": 5386,
      "index": 366,
      "value": [
        "　半開きの赤い口から唾液が糸を引いて、テラテラと光る亀頭と繋がっ",
        "/C"
      ]
    },
    {
      "op": "44",
      "offset": 5432,
      "index": 367,
      "value": [
        "ている。",
        "/E"
      ]
    },
    {
      "op": "24",
      "offset": 5438,
      "index": 368,
      "value": [
        "u8:4",
        "u8:149",
        "u8:1"
      ]
    },
    {
      "op": "4A",
      "offset": 5442,
      "index": 369,
      "value": [
        "セシリア",
        "/E"
      ]
    },
    {
      "op": "44",
      "offset": 5448,
      "index": 370,
      "value": [
        "「アアン……ハア……ア……」",
        "/E"
      ]
    },
    {
      "op": "4A",
      "offset": 5464,
      "index": 371,
      "value": [
        "",
        "/E"
      ]
    },
    {
      "op": "44",
      "offset": 5466,
      "index": 372,
      "value": [
        "　暴発は免れた。",
        "/W"
      ]
    },
    {
      "op": "44",
      "offset": 5479,
      "index": 373,
      "value": [
        "　口に出すなど、いつでもできる。",
        "/E"
      ]
    },
    {
      "op": "44",
      "offset": 5499,
      "index": 374,
      "value": [
        "　今はそれより、セシリアに確実に烙印を刻み込まなければ。",
        "/E"
      ]
    },
    {
      "op": "4A",
      "offset": 5536,
      "index": 375,
      "value": [
        "N1",
        "/E"
      ]
    },
    {
      "op": "44",
      "offset": 5539,
      "index": 376,
      "value": [
        "「立て、セシリア。",
        "/C"
      ]
    },
    {
      "op": "44",
      "offset": 5551,
      "index": 377,
      "value": [
        "　立って壁に手をつくんだ」",
        "/E"
      ]
    },
    {
      "op": "4A",
      "offset": 5569,
      "index": 378,
      "value": [
        "",
        "/E"
      ]
    },
    {
      "op": "44",
      "offset": 5571,
      "index": 379,
      "value": [
        "　腕を引いて立たせ、肩を小突いた。",
        "/W"
      ]
    },
    {
      "op": "44",
      "offset": 5596,
      "index": 380,
      "value": [
        "　肩で息をするセシリアは、よろめきながらも後ろを向いた。",
        "/E"
      ]
    },
    {
      "op": "43",
      "offset": 5630,
      "index": 381,
      "value": []
    },
    {
      "op": "34",
      "offset": 5631,
      "index": 382,
      "value": []
    },
    {
      "op": "28",
      "offset": 5632,
      "index": 383,
      "value": [
        "u8:4",
        "u8:8",
        "u8:0"
      ]
    },
    {
      "op": "3B",
      "offset": 5636,
      "index": 384,
      "value": [
        "u8:1",
        "u8:29",
        "u8:4",
        "u8:3"
      ]
    },
    {
      "op": "42",
      "offset": 5641,
      "index": 385,
      "value": []
    },
    {
      "op": "44",
      "offset": 5642,
      "index": 386,
      "value": [
        "　倒れそうな体を支えるように、個室の壁に両手をつく。",
        "/E"
      ]
    },
    {
      "op": "4A",
      "offset": 5678,
      "index": 387,
      "value": [
        "N1",
        "/E"
      ]
    },
    {
      "op": "44",
      "offset": 5681,
      "index": 388,
      "value": [
        "「よし、そのまま動くなよ」",
        "/E"
      ]
    },
    {
      "op": "4A",
      "offset": 5697,
      "index": 389,
      "value": [
        "",
        "/E"
      ]
    },
    {
      "op": "44",
      "offset": 5699,
      "index": 390,
      "value": [
        "　ドレスの裾をまくり上げた。",
        "/W"
      ]
    },
    {
      "op": "44",
      "offset": 5717,
      "index": 391,
      "value": [
        "　白くなめらかな下肢。",
        "/W"
      ]
    },
    {
      "op": "44",
      "offset": 5733,
      "index": 392,
      "value": [
        "　細い足首に続く、柔らかそうなふくらはぎ。",
        "/E"
      ]
    },
    {
      "op": "44",
      "offset": 5761,
      "index": 393,
      "value": [
        "　すんなり伸びた膝の上の腿はむっちりと張りつめて、乳色に光って",
        "/C"
      ]
    },
    {
      "op": "44",
      "offset": 5802,
      "index": 394,
      "value": [
        "いる。",
        "/W"
      ]
    },
    {
      "op": "44",
      "offset": 5807,
      "index": 395,
      "value": [
        "　その上の尻は充分に熟し、小さな下着を持ち上げる。",
        "/E"
      ]
    },
    {
      "op": "44",
      "offset": 5844,
      "index": 396,
      "value": [
        "　下着に手をかけた。",
        "/W"
      ]
    },
    {
      "op": "44",
      "offset": 5859,
      "index": 397,
      "value": [
        "　わずかに湿っている。",
        "/W"
      ]
    },
    {
      "op": "44",
      "offset": 5873,
      "index": 398,
      "value": [
        "　上気した肌の汗を吸ったのだろう。",
        "/E"
      ]
    },
    {
      "op": "44",
      "offset": 5897,
      "index": 399,
      "value": [
        "　そのまま、ずるっと引きおろす。",
        "/W"
      ]
    },
    {
      "op": "44",
      "offset": 5916,
      "index": 400,
      "value": [
        "　つんと上向いた尻で少し引っかかったが、無理やり膝まで下げた。",
        "/E"
      ]
    },
    {
      "op": "32",
      "offset": 5958,
      "index": 401,
      "value": []
    },
    {
      "op": "28",
      "offset": 5959,
      "index": 402,
      "value": [
        "u8:4",
        "u8:8",
        "u8:1"
      ]
    },
    {
      "op": "33",
      "offset": 5963,
      "index": 403,
      "value": [
        "u8:2"
      ]
    },
    {
      "op": "24",
      "offset": 5965,
      "index": 404,
      "value": [
        "u8:4",
        "u8:150",
        "u8:1"
      ]
    },
    {
      "op": "4A",
      "offset": 5969,
      "index": 405,
      "value": [
        "セシリア",
        "/E"
      ]
    },
    {
      "op": "44",
      "offset": 5975,
      "index": 406,
      "value": [
        "「ああ……はあ、ああっ」",
        "/E"
      ]
    },
    {
      "op": "4A",
      "offset": 5989,
      "index": 407,
      "value": [
        "",
        "/E"
      ]
    },
    {
      "op": "44",
      "offset": 5991,
      "index": 408,
      "value": [
        "　振り向こうとするセシリア。",
        "/W"
      ]
    },
    {
      "op": "44",
      "offset": 6009,
      "index": 409,
      "value": [
        "　腰のくびれを押さえつけ、動けないように固定した。",
        "/W"
      ]
    },
    {
      "op": "44",
      "offset": 6041,
      "index": 410,
      "value": [
        "　そのときだった。",
        "/E"
      ]
    },
    {
      "op": "44",
      "offset": 6052,
      "index": 411,
      "value": [
        "　扉を開ける音。",
        "/W"
      ]
    },
    {
      "op": "44",
      "offset": 6065,
      "index": 412,
      "value": [
        "　そして誰かが入ってくる気配。",
        "/E"
      ]
    },
    {
      "op": "44",
      "offset": 6086,
      "index": 413,
      "value": [
        "　セシリアが息を飲み、身を強張らせる。",
        "/W"
      ]
    },
    {
      "op": "44",
      "offset": 6112,
      "index": 414,
      "value": [
        "　俺も動きを止め気配を探った。",
        "/E"
      ]
    },
    {
      "op": "4A",
      "offset": 6135,
      "index": 415,
      "value": [
        "N1",
        "/E"
      ]
    },
    {
      "op": "44",
      "offset": 6138,
      "index": 416,
      "value": [
        "「……………………………………………………」",
        "/E"
      ]
    },
    {
      "op": "4A",
      "offset": 6162,
      "index": 417,
      "value": [
        "",
        "/E"
      ]
    },
    {
      "op": "44",
      "offset": 6164,
      "index": 418,
      "value": [
        "　便所に入ってきた足音は、まっすぐ小便器の方へ向かう。",
        "/W"
      ]
    },
    {
      "op": "44",
      "offset": 6203,
      "index": 419,
      "value": [
        "　使用中の個室に半裸の女がいるとは、夢にも思っていないだろう。",
        "/E"
      ]
    },
    {
      "op": "24",
      "offset": 6246,
      "index": 420,
      "value": [
        "u8:4",
        "u8:151",
        "u8:1"
      ]
    },
    {
      "op": "4A",
      "offset": 6250,
      "index": 421,
      "value": [
        "セシリア",
        "/E"
      ]
    },
    {
      "op": "44",
      "offset": 6256,
      "index": 422,
      "value": [
        "「ハアハア……ハア、ハア」",
        "/E"
      ]
    },
    {
      "op": "4A",
      "offset": 6271,
      "index": 423,
      "value": [
        "",
        "/E"
      ]
    },
    {
      "op": "44",
      "offset": 6273,
      "index": 424,
      "value": [
        "　むき出しの背中は汗ばんで、細かく震えている。",
        "/W"
      ]
    },
    {
      "op": "44",
      "offset": 6304,
      "index": 425,
      "value": [
        "　壁に手をつかせたせいで突き出している尻も、プルプルと怯えている。",
        "/E"
      ]
    },
    {
      "op": "4A",
      "offset": 6345,
      "index": 426,
      "value": [
        "N1",
        "/E"
      ]
    },
    {
      "op": "44",
      "offset": 6348,
      "index": 427,
      "value": [
        "「ふん……」",
        "/E"
      ]
    },
    {
      "op": "4A",
      "offset": 6356,
      "index": 428,
      "value": [
        "",
        "/E"
      ]
    },
    {
      "op": "44",
      "offset": 6358,
      "index": 429,
      "value": [
        "　充血してそびえ立つ剛直を、その尻にこすりつけた。",
        "/E"
      ]
    },
    {
      "op": "24",
      "offset": 6391,
      "index": 430,
      "value": [
        "u8:4",
        "u8:152",
        "u8:1"
      ]
    },
    {
      "op": "4A",
      "offset": 6395,
      "index": 431,
      "value": [
        "セシリア",
        "/E"
      ]
    },
    {
      "op": "44",
      "offset": 6401,
      "index": 432,
      "value": [
        "「……ンッ、アウッ」",
        "/E"
      ]
    },
    {
      "op": "4A",
      "offset": 6413,
      "index": 433,
      "value": [
        "",
        "/E"
      ]
    },
    {
      "op": "44",
      "offset": 6415,
      "index": 434,
      "value": [
        "　思わず漏らした声に、金の髪の生え際までが真っ赤に染まる。",
        "/W"
      ]
    },
    {
      "op": "44",
      "offset": 6456,
      "index": 435,
      "value": [
        "　怯えた目で振り返った。",
        "/W"
      ]
    },
    {
      "op": "44",
      "offset": 6474,
      "index": 436,
      "value": [
        "　顔に信じられないと書いてある。",
        "/E"
      ]
    },
    {
      "op": "4A",
      "offset": 6495,
      "index": 437,
      "value": [
        "N1",
        "/E"
      ]
    },
    {
      "op": "44",
      "offset": 6498,
      "index": 438,
      "value": [
        "「じっとしていろよ……」",
        "/E"
      ]
    },
    {
      "op": "4A",
      "offset": 6512,
      "index": 439,
      "value": [
        "",
        "/E"
      ]
    },
    {
      "op": "44",
      "offset": 6514,
      "index": 440,
      "value": [
        "　尻肉を左右に押し開く。",
        "/W"
      ]
    },
    {
      "op": "44",
      "offset": 6534,
      "index": 441,
      "value": [
        "　狭間にのぞく肉ひだは、今や濡れて光っていた。",
        "/W"
      ]
    },
    {
      "op": "44",
      "offset": 6565,
      "index": 442,
      "value": [
        "　柔らかそうな赤らんだ肉に、剛直を押し当てる。",
        "/E"
      ]
    },
    {
      "op": "24",
      "offset": 6597,
      "index": 443,
      "value": [
        "u8:4",
        "u8:153",
        "u8:1"
      ]
    },
    {
      "op": "4A",
      "offset": 6601,
      "index": 444,
      "value": [
        "セシリア",
        "/E"
      ]
    },
    {
      "op": "44",
      "offset": 6607,
      "index": 445,
      "value": [
        "「い……いや、まって……いまはっ」",
        "/E"
      ]
    },
    {
      "op": "4A",
      "offset": 6626,
      "index": 446,
      "value": [
        "",
        "/E"
      ]
    },
    {
      "op": "44",
      "offset": 6628,
      "index": 447,
      "value": [
        "　一気に中へ押し入った。",
        "/W"
      ]
    },
    {
      "op": "44",
      "offset": 6647,
      "index": 448,
      "value": [
        "　狭いが充分に濡れた膣内は、しなやかにうねって俺を飲み込む。",
        "/E"
      ]
    },
    {
      "op": "32",
      "offset": 6688,
      "index": 449,
      "value": []
    },
    {
      "op": "28",
      "offset": 6689,
      "index": 450,
      "value": [
        "u8:4",
        "u8:8",
        "u8:2"
      ]
    },
    {
      "op": "33",
      "offset": 6693,
      "index": 451,
      "value": [
        "u8:2"
      ]
    },
    {
      "op": "24",
      "offset": 6695,
      "index": 452,
      "value": [
        "u8:4",
        "u8:154",
        "u8:1"
      ]
    },
    {
      "op": "4A",
      "offset": 6699,
      "index": 453,
      "value": [
        "セシリア",
        "/E"
      ]
    },
    {
      "op": "44",
      "offset": 6705,
      "index": 454,
      "value": [
        "「んううっ！",
        "/C"
      ]
    },
    {
      "op": "44",
      "offset": 6713,
      "index": 455,
      "value": [
        "　あ……んんんっ」",
        "/E"
      ]
    },
    {
      "op": "4A",
      "offset": 6724,
      "index": 456,
      "value": [
        "",
        "/E"
      ]
    },
    {
      "op": "44",
      "offset": 6726,
      "index": 457,
      "value": [
        "　抑えきれない声が漏れる。",
        "/W"
      ]
    },
    {
      "op": "44",
      "offset": 6744,
      "index": 458,
      "value": [
        "　一旦深く挿入してから、ゆっくりと腰を引いた。",
        "/W"
      ]
    },
    {
      "op": "44",
      "offset": 6776,
      "index": 459,
      "value": [
        "　反り返った分身が、セシリアの内壁をこする。",
        "/E"
      ]
    },
    {
      "op": "24",
      "offset": 6806,
      "index": 460,
      "value": [
        "u8:4",
        "u8:155",
        "u8:1"
      ]
    },
    {
      "op": "4A",
      "offset": 6810,
      "index": 461,
      "value": [
        "セシリア",
        "/E"
      ]
    },
    {
      "op": "44",
      "offset": 6816,
      "index": 462,
      "value": [
        "「……っは……ああ……んく……ゥッ」",
        "/E"
      ]
    },
    {
      "op": "4A",
      "offset": 6836,
      "index": 463,
      "value": [
        "",
        "/E"
      ]
    },
    {
      "op": "44",
      "offset": 6838,
      "index": 464,
      "value": [
        "　必死に唇を噛んでいる。",
        "/W"
      ]
    },
    {
      "op": "44",
      "offset": 6856,
      "index": 465,
      "value": [
        "　外の人間は用を足し終わり、手を洗っているらしい。",
        "/W"
      ]
    },
    {
      "op": "44",
      "offset": 6891,
      "index": 466,
      "value": [
        "　俺は水音にささやき声を紛れさせた。",
        "/E"
      ]
    },
    {
      "op": "4A",
      "offset": 6916,
      "index": 467,
      "value": [
        "N1",
        "/E"
      ]
    },
    {
      "op": "44",
      "offset": 6919,
      "index": 468,
      "value": [
        "「我慢しなくていいんだぜ。",
        "/C"
      ]
    },
    {
      "op": "44",
      "offset": 6936,
      "index": 469,
      "value": [
        "　外の奴に、いやらしい声を聞かせてやれよ」",
        "/E"
      ]
    },
    {
      "op": "4A",
      "offset": 6963,
      "index": 470,
      "value": [
        "",
        "/E"
      ]
    },
    {
      "op": "32",
      "offset": 6965,
      "index": 471,
      "value": []
    },
    {
      "op": "28",
      "offset": 6966,
      "index": 472,
      "value": [
        "u8:4",
        "u8:8",
        "u8:3"
      ]
    },
    {
      "op": "33",
      "offset": 6970,
      "index": 473,
      "value": [
        "u8:2"
      ]
    },
    {
      "op": "24",
      "offset": 6972,
      "index": 474,
      "value": [
        "u8:4",
        "u8:156",
        "u8:1"
      ]
    },
    {
      "op": "4A",
      "offset": 6976,
      "index": 475,
      "value": [
        "セシリア",
        "/E"
      ]
    },
    {
      "op": "44",
      "offset": 6982,
      "index": 476,
      "value": [
        "「ウ、ウウ……ウウウッ！」",
        "/E"
      ]
    },
    {
      "op": "4A",
      "offset": 6997,
      "index": 477,
      "value": [
        "",
        "/E"
      ]
    },
    {
      "op": "44",
      "offset": 6999,
      "index": 478,
      "value": [
        "　ブンブンと首を振る。",
        "/E"
      ]
    },
    {
      "op": "4A",
      "offset": 7014,
      "index": 479,
      "value": [
        "N1",
        "/E"
      ]
    },
    {
      "op": "44",
      "offset": 7017,
      "index": 480,
      "value": [
        "「遠慮するなよ……」",
        "/E"
      ]
    },
    {
      "op": "4A",
      "offset": 7031,
      "index": 481,
      "value": [
        "",
        "/E"
      ]
    },
    {
      "op": "44",
      "offset": 7033,
      "index": 482,
      "value": [
        "　ぐいっと勢いよく突き上げる。",
        "/W"
      ]
    },
    {
      "op": "44",
      "offset": 7053,
      "index": 483,
      "value": [
        "　セシリアの体が硬直した。",
        "/E"
      ]
    },
    {
      "op": "24",
      "offset": 7071,
      "index": 484,
      "value": [
        "u8:4",
        "u8:157",
        "u8:1"
      ]
    },
    {
      "op": "4A",
      "offset": 7075,
      "index": 485,
      "value": [
        "セシリア",
        "/E"
      ]
    },
    {
      "op": "44",
      "offset": 7081,
      "index": 486,
      "value": [
        "「あっ……だっ、だめぇ……ンンンッ」",
        "/E"
      ]
    },
    {
      "op": "4A",
      "offset": 7101,
      "index": 487,
      "value": [
        "",
        "/E"
      ]
    },
    {
      "op": "44",
      "offset": 7103,
      "index": 488,
      "value": [
        "　声を殺して耐える。",
        "/W"
      ]
    },
    {
      "op": "44",
      "offset": 7118,
      "index": 489,
      "value": [
        "　身をよじるのを、壁に押さえつけた。",
        "/W"
      ]
    },
    {
      "op": "44",
      "offset": 7141,
      "index": 490,
      "value": [
        "　とろけるような柔肉を強引に突きえぐる。",
        "/E"
      ]
    },
    {
      "op": "24",
      "offset": 7168,
      "index": 491,
      "value": [
        "u8:4",
        "u8:158",
        "u8:1"
      ]
    },
    {
      "op": "4A",
      "offset": 7172,
      "index": 492,
      "value": [
        "セシリア",
        "/E"
      ]
    },
    {
      "op": "44",
      "offset": 7178,
      "index": 493,
      "value": [
        "「う、あ……お、お、おう……っ」",
        "/E"
      ]
    },
    {
      "op": "4A",
      "offset": 7196,
      "index": 494,
      "value": [
        "",
        "/E"
      ]
    },
    {
      "op": "44",
      "offset": 7198,
      "index": 495,
      "value": [
        "　震えながら手を伸ばしてくる。",
        "/W"
      ]
    },
    {
      "op": "44",
      "offset": 7218,
      "index": 496,
      "value": [
        "　俺の動きをけん制しようというのか。",
        "/W"
      ]
    },
    {
      "op": "44",
      "offset": 7241,
      "index": 497,
      "value": [
        "　軽くいなし、律動にひねりを加えてやる。",
        "/E"
      ]
    },
    {
      "op": "24",
      "offset": 7267,
      "index": 498,
      "value": [
        "u8:4",
        "u8:159",
        "u8:1"
      ]
    },
    {
      "op": "4A",
      "offset": 7271,
      "index": 499,
      "value": [
        "セシリア",
        "/E"
      ]
    },
    {
      "op": "44",
      "offset": 7277,
      "index": 500,
      "value": [
        "「フクウッ……んっくう……う、んんっ」",
        "/E"
      ]
    },
    {
      "op": "4A",
      "offset": 7298,
      "index": 501,
      "value": [
        "",
        "/E"
      ]
    },
    {
      "op": "44",
      "offset": 7300,
      "index": 502,
      "value": [
        "　ドクンと大量に吐き出される蜜。",
        "/W"
      ]
    },
    {
      "op": "44",
      "offset": 7323,
      "index": 503,
      "value": [
        "　ぬらぬらと太腿を濡らして垂れ落ちた。",
        "/E"
      ]
    },
    {
      "op": "24",
      "offset": 7349,
      "index": 504,
      "value": [
        "u8:4",
        "u8:160",
        "u8:1"
      ]
    },
    {
      "op": "4A",
      "offset": 7353,
      "index": 505,
      "value": [
        "セシリア",
        "/E"
      ]
    },
    {
      "op": "44",
      "offset": 7359,
      "index": 506,
      "value": [
        "「あああ、そ、それ……だめぇ。",
        "/C"
      ]
    },
    {
      "op": "44",
      "offset": 7376,
      "index": 507,
      "value": [
        "　も、もう……オオウッ……っ！」",
        "/E"
      ]
    },
    {
      "op": "4A",
      "offset": 7394,
      "index": 508,
      "value": [
        "",
        "/E"
      ]
    },
    {
      "op": "44",
      "offset": 7396,
      "index": 509,
      "value": [
        "　耐えきれないように、セシリアが上ずった声をあげる。",
        "/W"
      ]
    },
    {
      "op": "44",
      "offset": 7427,
      "index": 510,
      "value": [
        "　同時に扉が閉まる音。",
        "/W"
      ]
    },
    {
      "op": "44",
      "offset": 7445,
      "index": 511,
      "value": [
        "　出ていったか。",
        "/E"
      ]
    },
    {
      "op": "44",
      "offset": 7456,
      "index": 512,
      "value": [
        "　一瞬遅れて、金髪の流れる華奢な背中がガクガクと震え出した。",
        "/E"
      ]
    },
    {
      "op": "32",
      "offset": 7500,
      "index": 513,
      "value": []
    },
    {
      "op": "28",
      "offset": 7501,
      "index": 514,
      "value": [
        "u8:4",
        "u8:8",
        "u8:4"
      ]
    },
    {
      "op": "33",
      "offset": 7505,
      "index": 515,
      "value": [
        "u8:2"
      ]
    },
    {
      "op": "24",
      "offset": 7507,
      "index": 516,
      "value": [
        "u8:4",
        "u8:161",
        "u8:1"
      ]
    },
    {
      "op": "4A",
      "offset": 7511,
      "index": 517,
      "value": [
        "セシリア",
        "/E"
      ]
    },
    {
      "op": "44",
      "offset": 7517,
      "index": 518,
      "value": [
        "「あっ……あああっっ！",
        "/C"
      ]
    },
    {
      "op": "44",
      "offset": 7530,
      "index": 519,
      "value": [
        "　ふ、くう……あはあああんっ」",
        "/E"
      ]
    },
    {
      "op": "4A",
      "offset": 7547,
      "index": 520,
      "value": [
        "",
        "/E"
      ]
    },
    {
      "op": "44",
      "offset": 7549,
      "index": 521,
      "value": [
        "　気が緩んだのか、今までこらえていた分声を張り上げる。",
        "/W"
      ]
    },
    {
      "op": "44",
      "offset": 7585,
      "index": 522,
      "value": [
        "　すかさず抽送を繰り返してやった。",
        "/E"
      ]
    },
    {
      "op": "24",
      "offset": 7608,
      "index": 523,
      "value": [
        "u8:4",
        "u8:162",
        "u8:1"
      ]
    },
    {
      "op": "4A",
      "offset": 7612,
      "index": 524,
      "value": [
        "セシリア",
        "/E"
      ]
    },
    {
      "op": "44",
      "offset": 7618,
      "index": 525,
      "value": [
        "「オオウ、アッアアッ、はあぁん……あっあっ、フウンッ！",
        "/C"
      ]
    },
    {
      "op": "44",
      "offset": 7647,
      "index": 526,
      "value": [
        "　だっ、だめよおっ……ああっ、こんな……あはああっ」",
        "/E"
      ]
    },
    {
      "op": "4A",
      "offset": 7675,
      "index": 527,
      "value": [
        "",
        "/E"
      ]
    },
    {
      "op": "4A",
      "offset": 7677,
      "index": 528,
      "value": [
        "N1",
        "/E"
      ]
    },
    {
      "op": "44",
      "offset": 7680,
      "index": 529,
      "value": [
        "「いやらしい女だな、大声あげて。",
        "/C"
      ]
    },
    {
      "op": "44",
      "offset": 7701,
      "index": 530,
      "value": [
        "　また誰かが入ってくるぞ？」",
        "/E"
      ]
    },
    {
      "op": "4A",
      "offset": 7719,
      "index": 531,
      "value": [
        "",
        "/E"
      ]
    },
    {
      "op": "24",
      "offset": 7721,
      "index": 532,
      "value": [
        "u8:4",
        "u8:163",
        "u8:1"
      ]
    },
    {
      "op": "4A",
      "offset": 7725,
      "index": 533,
      "value": [
        "セシリア",
        "/E"
      ]
    },
    {
      "op": "44",
      "offset": 7731,
      "index": 534,
      "value": [
        "「やっ……イヤァッ！",
        "/C"
      ]
    },
    {
      "op": "44",
      "offset": 7743,
      "index": 535,
      "value": [
        "　あっあっ、だめ……駄目えっ、とっ、とまら……ないいっ！」",
        "/E"
      ]
    },
    {
      "op": "4A",
      "offset": 7776,
      "index": 536,
      "value": [
        "",
        "/E"
      ]
    },
    {
      "op": "44",
      "offset": 7778,
      "index": 537,
      "value": [
        "　一旦堰を切った快感は、止めようとしても止まらない。",
        "/W"
      ]
    },
    {
      "op": "44",
      "offset": 7814,
      "index": 538,
      "value": [
        "　言葉で嬲られ、セシリアの理性は飛んでいた。",
        "/W"
      ]
    },
    {
      "op": "44",
      "offset": 7844,
      "index": 539,
      "value": [
        "　嬲った俺自身も興奮していた。",
        "/E"
      ]
    },
    {
      "op": "44",
      "offset": 7867,
      "index": 540,
      "value": [
        "　激しく女体を突き上げる。",
        "/E"
      ]
    },
    {
      "op": "24",
      "offset": 7887,
      "index": 541,
      "value": [
        "u8:4",
        "u8:164",
        "u8:1"
      ]
    },
    {
      "op": "4A",
      "offset": 7891,
      "index": 542,
      "value": [
        "セシリア",
        "/E"
      ]
    },
    {
      "op": "44",
      "offset": 7897,
      "index": 543,
      "value": [
        "「あふ……ああぁーっ、あーっ……すごい、おうっ、これえっ！",
        "/C"
      ]
    },
    {
      "op": "44",
      "offset": 7928,
      "index": 544,
      "value": [
        "　オオウッ、奥までっ……かっ、硬いのが奥までえっ」",
        "/E"
      ]
    },
    {
      "op": "4A",
      "offset": 7958,
      "index": 545,
      "value": [
        "",
        "/E"
      ]
    },
    {
      "op": "44",
      "offset": 7960,
      "index": 546,
      "value": [
        "　締まる内部に強引に抜き差しすると、肉ひだがめくれる感触がある。",
        "/W"
      ]
    },
    {
      "op": "44",
      "offset": 8004,
      "index": 547,
      "value": [
        "　肉棒を伝ってあふれ出したセシリアの愛液がしたたり、床に丸く跡を",
        "/C"
      ]
    },
    {
      "op": "44",
      "offset": 8047,
      "index": 548,
      "value": [
        "つける。",
        "/E"
      ]
    },
    {
      "op": "24",
      "offset": 8053,
      "index": 549,
      "value": [
        "u8:4",
        "u8:165",
        "u8:1"
      ]
    },
    {
      "op": "4A",
      "offset": 8057,
      "index": 550,
      "value": [
        "セシリア",
        "/E"
      ]
    },
    {
      "op": "44",
      "offset": 8063,
      "index": 551,
      "value": [
        "「おお……すごい……アハアッ、ンンッ、かっ……感じちゃうっ！」",
        "/E"
      ]
    },
    {
      "op": "4A",
      "offset": 8097,
      "index": 552,
      "value": [
        "",
        "/E"
      ]
    },
    {
      "op": "4A",
      "offset": 8099,
      "index": 553,
      "value": [
        "N1",
        "/E"
      ]
    },
    {
      "op": "44",
      "offset": 8102,
      "index": 554,
      "value": [
        "「ほら……やっぱりいやらしい女だ」",
        "/E"
      ]
    },
    {
      "op": "4A",
      "offset": 8122,
      "index": 555,
      "value": [
        "",
        "/E"
      ]
    },
    {
      "op": "24",
      "offset": 8124,
      "index": 556,
      "value": [
        "u8:4",
        "u8:166",
        "u8:1"
      ]
    },
    {
      "op": "4A",
      "offset": 8128,
      "index": 557,
      "value": [
        "セシリア",
        "/E"
      ]
    },
    {
      "op": "44",
      "offset": 8134,
      "index": 558,
      "value": [
        "「ウウッ、ちが……違うわっ！",
        "/C"
      ]
    },
    {
      "op": "44",
      "offset": 8151,
      "index": 559,
      "value": [
        "　わ……わたしは、いや、らしく、なんてっ……ハアウッ！」",
        "/E"
      ]
    },
    {
      "op": "4A",
      "offset": 8181,
      "index": 560,
      "value": [
        "",
        "/E"
      ]
    },
    {
      "op": "44",
      "offset": 8183,
      "index": 561,
      "value": [
        "　切れ切れの声が、せっぱ詰まった調子を帯びる。",
        "/W"
      ]
    },
    {
      "op": "44",
      "offset": 8215,
      "index": 562,
      "value": [
        "　俺の昂ぶりも最高潮だった。",
        "/W"
      ]
    },
    {
      "op": "44",
      "offset": 8236,
      "index": 563,
      "value": [
        "　豊かな尻の中心を激しく突き上げる。",
        "/E"
      ]
    },
    {
      "op": "44",
      "offset": 8263,
      "index": 564,
      "value": [
        "　グシュグシュと蜜が飛び散って泡立つ。",
        "/W"
      ]
    },
    {
      "op": "44",
      "offset": 8289,
      "index": 565,
      "value": [
        "　肉ひだは必死にすがり付いてくる。",
        "/W"
      ]
    },
    {
      "op": "44",
      "offset": 8312,
      "index": 566,
      "value": [
        "　巻きついてくるのを無理やり引き剥がすと、ゾクゾクと快感が走った。",
        "/E"
      ]
    },
    {
      "op": "24",
      "offset": 8355,
      "index": 567,
      "value": [
        "u8:4",
        "u8:167",
        "u8:1"
      ]
    },
    {
      "op": "4A",
      "offset": 8359,
      "index": 568,
      "value": [
        "セシリア",
        "/E"
      ]
    },
    {
      "op": "44",
      "offset": 8365,
      "index": 569,
      "value": [
        "「アハッ、アアンッ……はあぁっ……オホオウウッ！",
        "/C"
      ]
    },
    {
      "op": "44",
      "offset": 8391,
      "index": 570,
      "value": [
        "　そんなはげしくっ……ハアアンッ、アアーッ！」",
        "/E"
      ]
    },
    {
      "op": "4A",
      "offset": 8416,
      "index": 571,
      "value": [
        "",
        "/E"
      ]
    },
    {
      "op": "4A",
      "offset": 8418,
      "index": 572,
      "value": [
        "N1",
        "/E"
      ]
    },
    {
      "op": "44",
      "offset": 8421,
      "index": 573,
      "value": [
        "「そんなに感じまくって、よく違うなんて言えるな？",
        "/C"
      ]
    },
    {
      "op": "44",
      "offset": 8450,
      "index": 574,
      "value": [
        "　びっしょり濡れてヒクヒクしているくせに」",
        "/E"
      ]
    },
    {
      "op": "4A",
      "offset": 8474,
      "index": 575,
      "value": [
        "",
        "/E"
      ]
    },
    {
      "op": "24",
      "offset": 8476,
      "index": 576,
      "value": [
        "u8:4",
        "u8:168",
        "u8:1"
      ]
    },
    {
      "op": "4A",
      "offset": 8480,
      "index": 577,
      "value": [
        "セシリア",
        "/E"
      ]
    },
    {
      "op": "44",
      "offset": 8486,
      "index": 578,
      "value": [
        "「アアアンッ、アハアッ……だっ、だってっ！",
        "/C"
      ]
    },
    {
      "op": "44",
      "offset": 8509,
      "index": 579,
      "value": [
        "　こんなにっ……か、硬いのっ、オオオウッ……硬いのがあっ！",
        "/C"
      ]
    },
    {
      "op": "44",
      "offset": 8542,
      "index": 580,
      "value": [
        "　ヒッ、ヒウッ、アアウッ……あはああーーっ！！」",
        "/E"
      ]
    },
    {
      "op": "4A",
      "offset": 8568,
      "index": 581,
      "value": [
        "",
        "/E"
      ]
    },
    {
      "op": "08",
      "offset": 8570,
      "index": 582,
      "value": [
        "u8:33",
        "u8:0",
        "u8:3",
        "u8:0"
      ]
    },
    {
      "op": "1A",
      "offset": 8575,
      "index": 583,
      "value": [
        "u16:285"
      ]
    },
    {
      "op": "08",
      "offset": 8578,
      "index": 584,
      "value": [
        "u8:34",
        "u8:0",
        "u8:3",
        "u8:0"
      ]
    },
    {
      "op": "1A",
      "offset": 8583,
      "index": 585,
      "value": [
        "u16:286"
      ]
    },
    {
      "op": "47",
      "offset": 8586,
      "index": 586,
      "value": [
        "u8:2"
      ]
    },
    {
      "op": "44",
      "offset": 8588,
      "index": 587,
      "value": [
        "中に出す",
        "/E"
      ]
    },
    {
      "op": "44",
      "offset": 8596,
      "index": 588,
      "value": [
        "外に出す",
        "/E"
      ]
    },
    {
      "op": "49",
      "offset": 8604,
      "index": 589,
      "value": [
        "u8:1",
        "u16:4"
      ]
    },
    {
      "op": "49",
      "offset": 8608,
      "index": 590,
      "value": [
        "u8:2",
        "u16:3"
      ]
    },
    {
      "op": "1A",
      "offset": 8612,
      "index": 591,
      "value": [
        "u16:285"
      ]
    },
    {
      "op": "1A",
      "offset": 8615,
      "index": 592,
      "value": [
        "u16:286"
      ]
    },
    {
      "op": "00",
      "offset": 8618,
      "index": 593,
      "value": []
    },
    {
      "op": "00",
      "offset": 8619,
      "index": 594,
      "value": []
    }
  ]
}