{
  "size": 2916,
  "opcodes": [
    {
      "op": "05",
      "offset": 0,
      "index": 0,
      "value": [
        "u16:461"
      ]
    },
    {
      "op": "05",
      "offset": 3,
      "index": 1,
      "value": [
        "u16:1415"
      ]
    },
    {
      "op": "24",
      "offset": 6,
      "index": 2,
      "value": [
        "u8:7",
        "u8:43",
        "u8:1"
      ]
    },
    {
      "op": "4A",
      "offset": 10,
      "index": 3,
      "value": [
        "りんご",
        "/E"
      ]
    },
    {
      "op": "44",
      "offset": 15,
      "index": 4,
      "value": [
        "「……………………………………………………」",
        "/E"
      ]
    },
    {
      "op": "4A",
      "offset": 39,
      "index": 5,
      "value": [
        "",
        "/E"
      ]
    },
    {
      "op": "44",
      "offset": 41,
      "index": 6,
      "value": [
        "　少女は怯えた表情で俺を迎える。",
        "/E"
      ]
    },
    {
      "op": "44",
      "offset": 66,
      "index": 7,
      "value": [
        "　…………そうだ。",
        "/W"
      ]
    },
    {
      "op": "44",
      "offset": 77,
      "index": 8,
      "value": [
        "　確かに、俺を迎えていた。",
        "/E"
      ]
    },
    {
      "op": "44",
      "offset": 95,
      "index": 9,
      "value": [
        "　表情は怯え、蒼白になって震えている。",
        "/W"
      ]
    },
    {
      "op": "44",
      "offset": 122,
      "index": 10,
      "value": [
        "　それでも、りんごは俺を待っていた。",
        "/W"
      ]
    },
    {
      "op": "44",
      "offset": 144,
      "index": 11,
      "value": [
        "　言葉として聞かなくても、俺にはわかった。",
        "/E"
      ]
    },
    {
      "op": "44",
      "offset": 171,
      "index": 12,
      "value": [
        "　むろん、俺に与えられる恐怖と苦痛を、待ち望んでいるわけではない",
        "/C"
      ]
    },
    {
      "op": "44",
      "offset": 213,
      "index": 13,
      "value": [
        "だろう。",
        "/W"
      ]
    },
    {
      "op": "44",
      "offset": 219,
      "index": 14,
      "value": [
        "　もっと奥深い根底の部分で、りんごは待っているのだった。",
        "/E"
      ]
    },
    {
      "op": "20",
      "offset": 256,
      "index": 15,
      "value": [
        "u8:3",
        "u8:255"
      ]
    },
    {
      "op": "43",
      "offset": 259,
      "index": 16,
      "value": []
    },
    {
      "op": "32",
      "offset": 260,
      "index": 17,
      "value": []
    },
    {
      "op": "2F",
      "offset": 261,
      "index": 18,
      "value": [
        "u8:2",
        "u8:0"
      ]
    },
    {
      "op": "2F",
      "offset": 264,
      "index": 19,
      "value": [
        "u8:3",
        "u8:0"
      ]
    },
    {
      "op": "27",
      "offset": 267,
      "index": 20,
      "value": [
        "u16:256"
      ]
    },
    {
      "op": "33",
      "offset": 270,
      "index": 21,
      "value": [
        "u8:4"
      ]
    },
    {
      "op": "42",
      "offset": 272,
      "index": 22,
      "value": []
    },
    {
      "op": "44",
      "offset": 273,
      "index": 23,
      "value": [
        "　座卓の上に、生白い裸体がボウッと浮かび上がる。",
        "/W"
      ]
    },
    {
      "op": "44",
      "offset": 308,
      "index": 24,
      "value": [
        "　四肢を座卓の脚に縛りつけられ、解剖を待つ蛙のように不安定な姿で",
        "/C"
      ]
    },
    {
      "op": "44",
      "offset": 356,
      "index": 25,
      "value": [
        "りんごは泣きじゃくっていた。",
        "/E"
      ]
    },
    {
      "op": "24",
      "offset": 373,
      "index": 26,
      "value": [
        "u8:7",
        "u8:44",
        "u8:1"
      ]
    },
    {
      "op": "4A",
      "offset": 377,
      "index": 27,
      "value": [
        "りんご",
        "/E"
      ]
    },
    {
      "op": "44",
      "offset": 382,
      "index": 28,
      "value": [
        "「う……うっく……あう……う」",
        "/E"
      ]
    },
    {
      "op": "4A",
      "offset": 399,
      "index": 29,
      "value": [
        "",
        "/E"
      ]
    },
    {
      "op": "44",
      "offset": 401,
      "index": 30,
      "value": [
        "　目尻から流れ落ちた涙が、髪の中に消えている。",
        "/W"
      ]
    },
    {
      "op": "44",
      "offset": 434,
      "index": 31,
      "value": [
        "　当然のように、手足には傷跡一つ残っていない。",
        "/E"
      ]
    },
    {
      "op": "44",
      "offset": 467,
      "index": 32,
      "value": [
        "　部屋の中から見つけ出した、今日の責め具を見せてやった。",
        "/W"
      ]
    },
    {
      "op": "44",
      "offset": 507,
      "index": 33,
      "value": [
        "　家人が使っているのだろう。",
        "/W"
      ]
    },
    {
      "op": "44",
      "offset": 526,
      "index": 34,
      "value": [
        "　古びた裁縫道具。",
        "/E"
      ]
    },
    {
      "op": "44",
      "offset": 542,
      "index": 35,
      "value": [
        "　中から一つの器具を選び出す。",
        "/W"
      ]
    },
    {
      "op": "44",
      "offset": 565,
      "index": 36,
      "value": [
        "　奇妙な形の道具。",
        "/W"
      ]
    },
    {
      "op": "44",
      "offset": 581,
      "index": 37,
      "value": [
        "　確か、くけ台という名前だったか。",
        "/E"
      ]
    },
    {
      "op": "44",
      "offset": 604,
      "index": 38,
      "value": [
        "　縫い物などをするとき、布をピンと張り、しわが寄らないようにする",
        "/C"
      ]
    },
    {
      "op": "44",
      "offset": 643,
      "index": 39,
      "value": [
        "道具だったと思う。",
        "/W"
      ]
    },
    {
      "op": "44",
      "offset": 657,
      "index": 40,
      "value": [
        "　ネジで金具を開け閉めし、間に布を挟めるようになっている。",
        "/E"
      ]
    },
    {
      "op": "4A",
      "offset": 695,
      "index": 41,
      "value": [
        "N1",
        "/E"
      ]
    },
    {
      "op": "44",
      "offset": 698,
      "index": 42,
      "value": [
        "「……さあ、りんご」",
        "/E"
      ]
    },
    {
      "op": "4A",
      "offset": 710,
      "index": 43,
      "value": [
        "",
        "/E"
      ]
    },
    {
      "op": "44",
      "offset": 712,
      "index": 44,
      "value": [
        "　開かれた脚の間に回った。",
        "/W"
      ]
    },
    {
      "op": "44",
      "offset": 731,
      "index": 45,
      "value": [
        "　露出しきっていない、未成熟な秘所に手を伸ばす。",
        "/W"
      ]
    },
    {
      "op": "44",
      "offset": 766,
      "index": 46,
      "value": [
        "　指先でつまむのがやっとの肉ひだを引っ張る。",
        "/E"
      ]
    },
    {
      "op": "24",
      "offset": 795,
      "index": 47,
      "value": [
        "u8:7",
        "u8:45",
        "u8:1"
      ]
    },
    {
      "op": "4A",
      "offset": 799,
      "index": 48,
      "value": [
        "りんご",
        "/E"
      ]
    },
    {
      "op": "44",
      "offset": 804,
      "index": 49,
      "value": [
        "「ぎゃああっ、痛いぃっ！",
        "/C"
      ]
    },
    {
      "op": "44",
      "offset": 819,
      "index": 50,
      "value": [
        "　やだあああっ」",
        "/E"
      ]
    },
    {
      "op": "4A",
      "offset": 829,
      "index": 51,
      "value": [
        "",
        "/E"
      ]
    },
    {
      "op": "44",
      "offset": 831,
      "index": 52,
      "value": [
        "　泣き声をあげるまで引いておいて、くけ台に挟み込んだ。",
        "/W"
      ]
    },
    {
      "op": "44",
      "offset": 866,
      "index": 53,
      "value": [
        "　手早くネジを締めてやる。",
        "/E"
      ]
    },
    {
      "op": "43",
      "offset": 884,
      "index": 54,
      "value": []
    },
    {
      "op": "34",
      "offset": 885,
      "index": 55,
      "value": []
    },
    {
      "op": "28",
      "offset": 886,
      "index": 56,
      "value": [
        "u8:7",
        "u8:4",
        "u8:0"
      ]
    },
    {
      "op": "3B",
      "offset": 890,
      "index": 57,
      "value": [
        "u8:1",
        "u8:29",
        "u8:4",
        "u8:3"
      ]
    },
    {
      "op": "42",
      "offset": 895,
      "index": 58,
      "value": []
    },
    {
      "op": "24",
      "offset": 896,
      "index": 59,
      "value": [
        "u8:7",
        "u8:46",
        "u8:1"
      ]
    },
    {
      "op": "4A",
      "offset": 900,
      "index": 60,
      "value": [
        "りんご",
        "/E"
      ]
    },
    {
      "op": "44",
      "offset": 905,
      "index": 61,
      "value": [
        "「ぎゃひいっ！！",
        "/C"
      ]
    },
    {
      "op": "44",
      "offset": 915,
      "index": 62,
      "value": [
        "　うあああっ、いたいいたいいっ！」",
        "/E"
      ]
    },
    {
      "op": "4A",
      "offset": 934,
      "index": 63,
      "value": [
        "",
        "/E"
      ]
    },
    {
      "op": "44",
      "offset": 936,
      "index": 64,
      "value": [
        "　痛みに大きくのけ反る。",
        "/W"
      ]
    },
    {
      "op": "44",
      "offset": 953,
      "index": 65,
      "value": [
        "　が、動く事はできない。",
        "/W"
      ]
    },
    {
      "op": "44",
      "offset": 969,
      "index": 66,
      "value": [
        "　女の中心部を繋ぎ止められてしまったのだ。",
        "/E"
      ]
    },
    {
      "op": "24",
      "offset": 998,
      "index": 67,
      "value": [
        "u8:7",
        "u8:47",
        "u8:1"
      ]
    },
    {
      "op": "4A",
      "offset": 1002,
      "index": 68,
      "value": [
        "りんご",
        "/E"
      ]
    },
    {
      "op": "44",
      "offset": 1007,
      "index": 69,
      "value": [
        "「ひっ、ひいん……ううっ……たすけて、たすけてえ」",
        "/E"
      ]
    },
    {
      "op": "4A",
      "offset": 1034,
      "index": 70,
      "value": [
        "",
        "/E"
      ]
    },
    {
      "op": "44",
      "offset": 1036,
      "index": 71,
      "value": [
        "　堅い板の上で必死に反り返る。",
        "/W"
      ]
    },
    {
      "op": "44",
      "offset": 1060,
      "index": 72,
      "value": [
        "　少しでも秘所に与えられた痛みを、軽減したいのだろう。",
        "/W"
      ]
    },
    {
      "op": "44",
      "offset": 1096,
      "index": 73,
      "value": [
        "　その乳首をつまみ上げる。",
        "/E"
      ]
    },
    {
      "op": "24",
      "offset": 1114,
      "index": 74,
      "value": [
        "u8:7",
        "u8:48",
        "u8:1"
      ]
    },
    {
      "op": "4A",
      "offset": 1118,
      "index": 75,
      "value": [
        "りんご",
        "/E"
      ]
    },
    {
      "op": "44",
      "offset": 1123,
      "index": 76,
      "value": [
        "「ひいっ……や、やめ……っ」",
        "/E"
      ]
    },
    {
      "op": "4A",
      "offset": 1139,
      "index": 77,
      "value": [
        "",
        "/E"
      ]
    },
    {
      "op": "44",
      "offset": 1141,
      "index": 78,
      "value": [
        "　もがく少女の、奇妙な形に持ち上げられた肉の先端を強くつぶす。",
        "/E"
      ]
    },
    {
      "op": "24",
      "offset": 1185,
      "index": 79,
      "value": [
        "u8:7",
        "u8:49",
        "u8:1"
      ]
    },
    {
      "op": "4A",
      "offset": 1189,
      "index": 80,
      "value": [
        "りんご",
        "/E"
      ]
    },
    {
      "op": "44",
      "offset": 1194,
      "index": 81,
      "value": [
        "「きひいいぃぃぃっ！！」",
        "/E"
      ]
    },
    {
      "op": "4A",
      "offset": 1208,
      "index": 82,
      "value": [
        "",
        "/E"
      ]
    },
    {
      "op": "22",
      "offset": 1210,
      "index": 83,
      "value": []
    },
    {
      "op": "2B",
      "offset": 1211,
      "index": 84,
      "value": [
        "u8:255",
        "u8:255",
        "u8:255"
      ]
    },
    {
      "op": "28",
      "offset": 1215,
      "index": 85,
      "value": [
        "u8:7",
        "u8:4",
        "u8:0"
      ]
    },
    {
      "op": "2C",
      "offset": 1219,
      "index": 86,
      "value": []
    },
    {
      "op": "44",
      "offset": 1220,
      "index": 87,
      "value": [
        "　チリッ",
        "/E"
      ]
    },
    {
      "op": "44",
      "offset": 1226,
      "index": 88,
      "value": [
        "　頭のどこかで、何かが焦げるような音がした。",
        "/E"
      ]
    },
    {
      "op": "20",
      "offset": 1254,
      "index": 89,
      "value": [
        "u8:13",
        "u8:255"
      ]
    },
    {
      "op": "44",
      "offset": 1257,
      "index": 90,
      "value": [
        "　気にかかったが、目の前の獲物が優先だ。",
        "/E"
      ]
    },
    {
      "op": "4A",
      "offset": 1286,
      "index": 91,
      "value": [
        "N1",
        "/E"
      ]
    },
    {
      "op": "44",
      "offset": 1289,
      "index": 92,
      "value": [
        "「少しは堪えてるみたいだな……」",
        "/E"
      ]
    },
    {
      "op": "4A",
      "offset": 1309,
      "index": 93,
      "value": [
        "",
        "/E"
      ]
    },
    {
      "op": "44",
      "offset": 1311,
      "index": 94,
      "value": [
        "　敏感な肉ひだは薄く伸ばされている。",
        "/W"
      ]
    },
    {
      "op": "44",
      "offset": 1336,
      "index": 95,
      "value": [
        "　軽く爪で弾いただけで、裂けてしまいそうだ。",
        "/W"
      ]
    },
    {
      "op": "44",
      "offset": 1364,
      "index": 96,
      "value": [
        "　くけ台をつまみ、引いてやる。",
        "/E"
      ]
    },
    {
      "op": "32",
      "offset": 1383,
      "index": 97,
      "value": []
    },
    {
      "op": "28",
      "offset": 1384,
      "index": 98,
      "value": [
        "u8:7",
        "u8:4",
        "u8:1"
      ]
    },
    {
      "op": "33",
      "offset": 1388,
      "index": 99,
      "value": [
        "u8:2"
      ]
    },
    {
      "op": "24",
      "offset": 1390,
      "index": 100,
      "value": [
        "u8:7",
        "u8:50",
        "u8:1"
      ]
    },
    {
      "op": "4A",
      "offset": 1394,
      "index": 101,
      "value": [
        "りんご",
        "/E"
      ]
    },
    {
      "op": "44",
      "offset": 1399,
      "index": 102,
      "value": [
        "「ギャアーッ！",
        "/C"
      ]
    },
    {
      "op": "44",
      "offset": 1408,
      "index": 103,
      "value": [
        "　いっ、いたああいっ、いたいよおおっ！」",
        "/E"
      ]
    },
    {
      "op": "4A",
      "offset": 1430,
      "index": 104,
      "value": [
        "",
        "/E"
      ]
    },
    {
      "op": "44",
      "offset": 1432,
      "index": 105,
      "value": [
        "　絶叫したりんごは、泡を吹き白目をむく。",
        "/W"
      ]
    },
    {
      "op": "44",
      "offset": 1460,
      "index": 106,
      "value": [
        "　それでも、激しい痛みに失神する事もできない。",
        "/W"
      ]
    },
    {
      "op": "44",
      "offset": 1490,
      "index": 107,
      "value": [
        "　震える全身には脂汗が浮かんでいる。",
        "/E"
      ]
    },
    {
      "op": "4A",
      "offset": 1516,
      "index": 108,
      "value": [
        "N1",
        "/E"
      ]
    },
    {
      "op": "44",
      "offset": 1519,
      "index": 109,
      "value": [
        "「苦しいのか？",
        "/C"
      ]
    },
    {
      "op": "44",
      "offset": 1529,
      "index": 110,
      "value": [
        "　自ら招いた事だ、仕方ないよなあ」",
        "/E"
      ]
    },
    {
      "op": "4A",
      "offset": 1553,
      "index": 111,
      "value": [
        "",
        "/E"
      ]
    },
    {
      "op": "44",
      "offset": 1555,
      "index": 112,
      "value": [
        "　笑いながら、包皮に包まれた肉芽をつまむ。",
        "/W"
      ]
    },
    {
      "op": "44",
      "offset": 1584,
      "index": 113,
      "value": [
        "　ビクッと震える。",
        "/E"
      ]
    },
    {
      "op": "24",
      "offset": 1596,
      "index": 114,
      "value": [
        "u8:7",
        "u8:51",
        "u8:1"
      ]
    },
    {
      "op": "4A",
      "offset": 1600,
      "index": 115,
      "value": [
        "りんご",
        "/E"
      ]
    },
    {
      "op": "44",
      "offset": 1605,
      "index": 116,
      "value": [
        "「アッ、アウ…………アウウ……」",
        "/E"
      ]
    },
    {
      "op": "4A",
      "offset": 1623,
      "index": 117,
      "value": [
        "",
        "/E"
      ]
    },
    {
      "op": "44",
      "offset": 1625,
      "index": 118,
      "value": [
        "　苦しげに歪んだ顔は、快感によるものではなさそうだ。",
        "/E"
      ]
    },
    {
      "op": "4A",
      "offset": 1658,
      "index": 119,
      "value": [
        "N1",
        "/E"
      ]
    },
    {
      "op": "44",
      "offset": 1661,
      "index": 120,
      "value": [
        "「痛いのか。",
        "/C"
      ]
    },
    {
      "op": "44",
      "offset": 1670,
      "index": 121,
      "value": [
        "　慣れればよくなる……とはいかないんだな」",
        "/E"
      ]
    },
    {
      "op": "4A",
      "offset": 1694,
      "index": 122,
      "value": [
        "",
        "/E"
      ]
    },
    {
      "op": "44",
      "offset": 1696,
      "index": 123,
      "value": [
        "　ふと気がつき、俺は驚いた。",
        "/W"
      ]
    },
    {
      "op": "44",
      "offset": 1715,
      "index": 124,
      "value": [
        "　どんな傷も、あっという間に治ってしまう。",
        "/W"
      ]
    },
    {
      "op": "44",
      "offset": 1741,
      "index": 125,
      "value": [
        "　それはつまり、破瓜の傷も癒えてしまうという事なのか。",
        "/E"
      ]
    },
    {
      "op": "44",
      "offset": 1775,
      "index": 126,
      "value": [
        "　再生した処女膜は、再び苦痛をもたらす。",
        "/W"
      ]
    },
    {
      "op": "44",
      "offset": 1805,
      "index": 127,
      "value": [
        "　りんごの身を守るはずの力が、彼女を苦しめるのだ。",
        "/E"
      ]
    },
    {
      "op": "44",
      "offset": 1838,
      "index": 128,
      "value": [
        "　だが、まさか本当にそんな事が？",
        "/E"
      ]
    },
    {
      "op": "4A",
      "offset": 1859,
      "index": 129,
      "value": [
        "N1",
        "/E"
      ]
    },
    {
      "op": "44",
      "offset": 1862,
      "index": 130,
      "value": [
        "「…………！」",
        "/E"
      ]
    },
    {
      "op": "4A",
      "offset": 1871,
      "index": 131,
      "value": [
        "",
        "/E"
      ]
    },
    {
      "op": "44",
      "offset": 1873,
      "index": 132,
      "value": [
        "　思いつき、くけ台で広げられた無防備な亀裂に、指を潜らせる。",
        "/E"
      ]
    },
    {
      "op": "32",
      "offset": 1915,
      "index": 133,
      "value": []
    },
    {
      "op": "28",
      "offset": 1916,
      "index": 134,
      "value": [
        "u8:7",
        "u8:4",
        "u8:0"
      ]
    },
    {
      "op": "33",
      "offset": 1920,
      "index": 135,
      "value": [
        "u8:2"
      ]
    },
    {
      "op": "24",
      "offset": 1922,
      "index": 136,
      "value": [
        "u8:7",
        "u8:52",
        "u8:1"
      ]
    },
    {
      "op": "4A",
      "offset": 1926,
      "index": 137,
      "value": [
        "りんご",
        "/E"
      ]
    },
    {
      "op": "44",
      "offset": 1931,
      "index": 138,
      "value": [
        "「う、うああっ！",
        "/C"
      ]
    },
    {
      "op": "44",
      "offset": 1941,
      "index": 139,
      "value": [
        "　やだ、やだ入れないでええっ！」",
        "/E"
      ]
    },
    {
      "op": "4A",
      "offset": 1960,
      "index": 140,
      "value": [
        "",
        "/E"
      ]
    },
    {
      "op": "44",
      "offset": 1962,
      "index": 141,
      "value": [
        "　押し返してくるような、独特の感触があった。",
        "/W"
      ]
    },
    {
      "op": "44",
      "offset": 1992,
      "index": 142,
      "value": [
        "　再生している。",
        "/E"
      ]
    },
    {
      "op": "44",
      "offset": 2004,
      "index": 143,
      "value": [
        "　指を揃え、グッと一気に押し込んだ。",
        "/W"
      ]
    },
    {
      "op": "44",
      "offset": 2030,
      "index": 144,
      "value": [
        "　ブツッと弾ける感覚があり、熱いものに包まれる。",
        "/E"
      ]
    },
    {
      "op": "32",
      "offset": 2061,
      "index": 145,
      "value": []
    },
    {
      "op": "28",
      "offset": 2062,
      "index": 146,
      "value": [
        "u8:7",
        "u8:4",
        "u8:1"
      ]
    },
    {
      "op": "33",
      "offset": 2066,
      "index": 147,
      "value": [
        "u8:2"
      ]
    },
    {
      "op": "24",
      "offset": 2068,
      "index": 148,
      "value": [
        "u8:7",
        "u8:53",
        "u8:1"
      ]
    },
    {
      "op": "4A",
      "offset": 2072,
      "index": 149,
      "value": [
        "りんご",
        "/E"
      ]
    },
    {
      "op": "44",
      "offset": 2077,
      "index": 150,
      "value": [
        "「ギャアアアァァァーーーーッッッ！！」",
        "/E"
      ]
    },
    {
      "op": "4A",
      "offset": 2098,
      "index": 151,
      "value": [
        "",
        "/E"
      ]
    },
    {
      "op": "44",
      "offset": 2100,
      "index": 152,
      "value": [
        "　じくっと指先が熱く濡れる。",
        "/W"
      ]
    },
    {
      "op": "44",
      "offset": 2120,
      "index": 153,
      "value": [
        "　破瓜の血か。",
        "/E"
      ]
    },
    {
      "op": "44",
      "offset": 2132,
      "index": 154,
      "value": [
        "　引き裂かれる苦痛に耐えかねて、りんごは泡立つ涎を垂れ流している。",
        "/E"
      ]
    },
    {
      "op": "4A",
      "offset": 2177,
      "index": 155,
      "value": [
        "N1",
        "/E"
      ]
    },
    {
      "op": "44",
      "offset": 2180,
      "index": 156,
      "value": [
        "「りんご、いいざまだな？」",
        "/E"
      ]
    },
    {
      "op": "4A",
      "offset": 2195,
      "index": 157,
      "value": [
        "",
        "/E"
      ]
    },
    {
      "op": "44",
      "offset": 2197,
      "index": 158,
      "value": [
        "　あざ笑い、剛直を取り出した。",
        "/W"
      ]
    },
    {
      "op": "44",
      "offset": 2219,
      "index": 159,
      "value": [
        "　筋張った幹を握り、しごきたてる。",
        "/W"
      ]
    },
    {
      "op": "44",
      "offset": 2242,
      "index": 160,
      "value": [
        "　たちまち快感が背骨を駆け上がる。",
        "/E"
      ]
    },
    {
      "op": "44",
      "offset": 2267,
      "index": 161,
      "value": [
        "　無残なりんごを目の前に、自慰をするときが最も気持ちいい。",
        "/W"
      ]
    },
    {
      "op": "44",
      "offset": 2307,
      "index": 162,
      "value": [
        "　その事に俺は気づいていた。",
        "/W"
      ]
    },
    {
      "op": "44",
      "offset": 2326,
      "index": 163,
      "value": [
        "　激しくこすり立て、責めたてる。",
        "/E"
      ]
    },
    {
      "op": "44",
      "offset": 2347,
      "index": 164,
      "value": [
        "　交接時と違い、早く昇り詰める事だけを目的にする。",
        "/W"
      ]
    },
    {
      "op": "44",
      "offset": 2384,
      "index": 165,
      "value": [
        "　頭の中が熱くなる。",
        "/E"
      ]
    },
    {
      "op": "4A",
      "offset": 2399,
      "index": 166,
      "value": [
        "N1",
        "/E"
      ]
    },
    {
      "op": "44",
      "offset": 2402,
      "index": 167,
      "value": [
        "「りんご……！」",
        "/E"
      ]
    },
    {
      "op": "4A",
      "offset": 2412,
      "index": 168,
      "value": [
        "",
        "/E"
      ]
    },
    {
      "op": "24",
      "offset": 2414,
      "index": 169,
      "value": [
        "u8:7",
        "u8:54",
        "u8:1"
      ]
    },
    {
      "op": "4A",
      "offset": 2418,
      "index": 170,
      "value": [
        "りんご",
        "/E"
      ]
    },
    {
      "op": "44",
      "offset": 2423,
      "index": 171,
      "value": [
        "「ア、アウ…………ア、ア……」",
        "/E"
      ]
    },
    {
      "op": "4A",
      "offset": 2440,
      "index": 172,
      "value": [
        "",
        "/E"
      ]
    },
    {
      "op": "44",
      "offset": 2442,
      "index": 173,
      "value": [
        "　空ろな視線は俺を見ていない。",
        "/W"
      ]
    },
    {
      "op": "44",
      "offset": 2464,
      "index": 174,
      "value": [
        "　それさえ快感だった。",
        "/W"
      ]
    },
    {
      "op": "44",
      "offset": 2479,
      "index": 175,
      "value": [
        "　急激に盛り上がる性感。",
        "/E"
      ]
    },
    {
      "op": "44",
      "offset": 2499,
      "index": 176,
      "value": [
        "　幹が太さを増す。",
        "/W"
      ]
    },
    {
      "op": "44",
      "offset": 2513,
      "index": 177,
      "value": [
        "　亀頭の傘が開く。",
        "/E"
      ]
    },
    {
      "op": "4A",
      "offset": 2528,
      "index": 178,
      "value": [
        "N1",
        "/E"
      ]
    },
    {
      "op": "44",
      "offset": 2531,
      "index": 179,
      "value": [
        "「くうっ」",
        "/E"
      ]
    },
    {
      "op": "4A",
      "offset": 2538,
      "index": 180,
      "value": [
        "",
        "/E"
      ]
    },
    {
      "op": "31",
      "offset": 2540,
      "index": 181,
      "value": [
        "u8:0",
        "u8:3"
      ]
    },
    {
      "op": "28",
      "offset": 2543,
      "index": 182,
      "value": [
        "u8:7",
        "u8:4",
        "u8:2"
      ]
    },
    {
      "op": "31",
      "offset": 2547,
      "index": 183,
      "value": [
        "u8:1",
        "u8:5"
      ]
    },
    {
      "op": "44",
      "offset": 2550,
      "index": 184,
      "value": [
        "　長くはもたなかった。",
        "/W"
      ]
    },
    {
      "op": "44",
      "offset": 2564,
      "index": 185,
      "value": [
        "　しびれるような下腹の快感を、ためらいなく解き放つ。",
        "/W"
      ]
    },
    {
      "op": "44",
      "offset": 2598,
      "index": 186,
      "value": [
        "　放物線を描いて飛び出す熱い飛沫。",
        "/E"
      ]
    },
    {
      "op": "44",
      "offset": 2626,
      "index": 187,
      "value": [
        "　りんごの顔に降りかかり、大部分が開けっ放しの口の中に飛び込む。",
        "/E"
      ]
    },
    {
      "op": "24",
      "offset": 2671,
      "index": 188,
      "value": [
        "u8:7",
        "u8:55",
        "u8:1"
      ]
    },
    {
      "op": "4A",
      "offset": 2675,
      "index": 189,
      "value": [
        "りんご",
        "/E"
      ]
    },
    {
      "op": "44",
      "offset": 2680,
      "index": 190,
      "value": [
        "「……っむぐぁっ！？",
        "/C"
      ]
    },
    {
      "op": "44",
      "offset": 2692,
      "index": 191,
      "value": [
        "　が……がはっ、けほっ……う、うぶぅ……っ」",
        "/E"
      ]
    },
    {
      "op": "4A",
      "offset": 2716,
      "index": 192,
      "value": [
        "",
        "/E"
      ]
    },
    {
      "op": "44",
      "offset": 2718,
      "index": 193,
      "value": [
        "　苦しげにむせている。",
        "/W"
      ]
    },
    {
      "op": "44",
      "offset": 2732,
      "index": 194,
      "value": [
        "　吐き出したくても、体の自由が利かない状態では、それもできない。",
        "/W"
      ]
    },
    {
      "op": "44",
      "offset": 2774,
      "index": 195,
      "value": [
        "　嗚咽する。",
        "/E"
      ]
    },
    {
      "op": "44",
      "offset": 2784,
      "index": 196,
      "value": [
        "　だらだらと、涎混じりの精液が頬を伝って流れ落ちる。",
        "/W"
      ]
    },
    {
      "op": "44",
      "offset": 2820,
      "index": 197,
      "value": [
        "　目を白黒させて、窒息寸前のようだ。",
        "/W"
      ]
    },
    {
      "op": "44",
      "offset": 2847,
      "index": 198,
      "value": [
        "　その異形に、俺は奇妙な満足感を抱いていた。",
        "/E"
      ]
    },
    {
      "op": "08",
      "offset": 2880,
      "index": 199,
      "value": [
        "u8:66",
        "u8:0",
        "u8:12",
        "u8:0"
      ]
    },
    {
      "op": "43",
      "offset": 2885,
      "index": 200,
      "value": []
    },
    {
      "op": "22",
      "offset": 2886,
      "index": 201,
      "value": []
    },
    {
      "op": "31",
      "offset": 2887,
      "index": 202,
      "value": [
        "u8:0",
        "u8:12"
      ]
    },
    {
      "op": "31",
      "offset": 2890,
      "index": 203,
      "value": [
        "u8:1",
        "u8:12"
      ]
    },
    {
      "op": "30",
      "offset": 2893,
      "index": 204,
      "value": [
        "u8:0",
        "u8:3"
      ]
    },
    {
      "op": "1E 1D",
      "offset": 2896,
      "index": 205,
      "value": [
        "u8:67"
      ]
    },
    {
      "op": "43",
      "offset": 2899,
      "index": 206,
      "value": []
    },
    {
      "op": "34",
      "offset": 2900,
      "index": 207,
      "value": []
    },
    {
      "op": "27",
      "offset": 2901,
      "index": 208,
      "value": [
        "u16:256"
      ]
    },
    {
      "op": "3B",
      "offset": 2904,
      "index": 209,
      "value": [
        "u8:1",
        "u8:29",
        "u8:4",
        "u8:3"
      ]
    },
    {
      "op": "42",
      "offset": 2909,
      "index": 210,
      "value": []
    },
    {
      "op": "1A",
      "offset": 2910,
      "index": 211,
      "value": [
        "u16:204"
      ]
    },
    {
      "op": "00",
      "offset": 2913,
      "index": 212,
      "value": []
    },
    {
      "op": "00",
      "offset": 2914,
      "index": 213,
      "value": []
    },
    {
      "op": "00",
      "offset": 2915,
      "index": 214,
      "value": []
    }
  ]
}